{
  "غبر": {
    "def": "غَبَرَ الرَّجُلُ يَغْبُرُ غُبُوراً: إذا (¬٨٥) مَكَثَ.\nوغُبَّرُ اللَّيْلِ: آخِرُه وبَقاياه.\nوالغُبْرُ: جماعَةُ الغابِر.\nوتَغَبَّرْتُ الناقَةَ: احْتَلَبْتَ غُبْرَها. وكَسَعْتُها بغُبْرِها (¬٨٦). وقَطَعَ اللَّهُ [/١٤٨ ب] غابِرَ فلانٍ ودابِرَه: أي آخِرَه وما بَقِيَ منه.\nوالتَّغْبِيْرُ: ارْتِفاعُ اللَّبَنِ.\nوالغُبْرَةُ: مَصْدَرُ الأغْبَرِ، غَبِرَ (¬٨٧) يَغْبَرُ غُبْرَةً.\nوالغُبَارُ: معروفٌ. والغَبَرَةُ (¬٨٨): لَطْخُهُ وتَرَدُّدُه. وفي مَثَلٍ (¬٨٩): «ما يُشَقُّ غُبَارُه».\nوالغَبَرَةُ: تَغَيُّرُ اللَّوْنِ الذي يَغْبَارُّ لِلْهَمِّ.\nوبَنُو غَبْرَاءَ: هُمُ اللُّصُوصُ. ويقال (¬٩٠): ابنُ غَبْرَاءَ ابنُ السَّبِيلِ.\nوالمُغَبِّرَةُ: قَوْمٌ يَذْكُرونَ اللَّهَ ﷿ بدُعاءٍ وإخْبَاتٍ. والتَّغْبِيْرُ: التَّهليلُ.\nوداهِيَةُ الغَبَرِ: لا يُهْتَدى للنَّجاءِ منها. وقيل: هي الحَيَّةُ.\nوعِرْقٌ غَبِرٌ: لا يَزَالُ (¬٩١) مُنْتَقِضاً.\n[والغَبْرَاءُ] (¬٩٢) من [الأرْضِ] (¬٩٣): الخَمَرُ (¬٩٤). ونَبْتٌ في السُّهولة.\nوالغُبَيْرَاءُ: فاكِهَةٌ. وهو في الحَدِيثِ: السُّكُرُّجَةُ (¬٩٥).\nورَجَعَ على غُبَيْرَاءِ ظَهْرِه: أي رَجَعَ بما يَكْرَهُ (¬٩٦). وأغْبَرْتُ (¬٩٧) في طَلَب الشَّيْءِ: انْكَمَشْت فيه.\nودارَةُ غُبَيْرٍ: لِبَني الأضْبَطِ بها ماءٌ يُقال له الغُبَيْر.\nبغر:",
    "pg": "5:75-77"
  },
  "غبس": {
    "def": "الغَبَسُ: لَوْنُ الرَّمادِ والذِّئبِ.\nوالغُبَيْسُ: الدَّهْرُ، تقول (¬٣٧): «لا أفْعَلُه ما غَبَا (¬٣٨) غُبَيْسٌ».\nوأتانا في غَبَسِ اللَّيْل: [أي] (¬٣٩) في آخِرِه حِينَ اشْتَدَّ سَوادُه. وأغْبَسَ اللَّيْلُ وأغْبَشَ: واحِدٌ. سبغ:",
    "pg": "5:17-18"
  },
  "غبط": {
    "def": "الغَبْطُ: الجَسُّ (¬١٥) باليَدِ لِيُعْرَفَ هُزَالُه من سِمَنِه، وناقَةٌ غَبُوْطٌ (¬١٦). وهو الشَّقُّ أيضاً.\nوالغِبْطَةُ: حُسْنُ الحالِ، رَجُلٌ مَغْبُوطٌ مُغْتَبَط (¬١٧).\nوالغَبِيْطَةُ (¬١٨): رَحْلٌ قَتَبُه وأحناؤه واحِدٌ (¬١٩).\nوفَرَسٌ مُغْبَطٌ في الكاثِبَة (¬٢٠): إذا كانَ مُرْتَفِعَ المَنْسِج.\nوالغُبْطَةُ من سُيُورِ المَزَادَةِ: سَيْرٌ مِثْلُ الشِّرَاكِ يُجْعَل على أطرافِ الأدِيمَيْنِ ثُمَّ (¬٢١) يُخْرَزُ [شَدِيداً] (¬٢٢).\nوالغُبُوْطُ: الحُزَمُ (¬٢٣) من الزَّرْع، واحِدُها غُبْطٌ (¬٢٤).\nوالغَبِيْطُ من الأرضِ والوادي: الواسِعُ.\nوأغْبَطَ عليه إغْبَاطاً: ألَحَّ عليه حتّى قَتَلَه (¬٢٥).\nوأغْبَطْتُ الرَّحْلَ (¬٢٦) على ظَهْرِ البَعِير إغْباطاً: أدَمْتَه.\n[وسَمَاءٌ] (¬٢٧) غَبَطى (¬٢٨): أغْبَطَت بالسَّحاب أيّاماً. وأغْبَطَتْ عليه السَّماءُ:\nدامَ مَطَرُها.\nبطغ (¬٢٩):\nبَطِغَ الرَّجُلُ-مِثْلُ بَدِغَ (¬٣٠) -: إذا تَلَطَّخَ بالعَذِرَة.\n\n\nغطم:",
    "pg": "5:32-33"
  },
  "غبن": {
    "def": "الغَبَنُ في الرَّأْي: الفائلُ (¬١٣)، وكذلك في البَيْع، غَبنْتُه (¬١٤) فهو مَغْبُونٌ.\nوالفاتِرُ عن العَمَل: غابِنٌ. والغَبِيْنَةُ: الغَبْنُ.\nو ﴿يَوْمُ التَّغابُنِ﴾ في الآخِرَةِ بالأعمال (¬١٥).\nوالغَبْنُ في الثَّوْبِ: كالعَطْفِ.\nوغَبِنْتُ الرَّجُلَ أغْبَنُه: إذا أغْفَلْتَه.\nوالمَغابِنُ: الأرْفاغُ والآباطُ، الواحِدُ مَغْبِنٌ. واغْتَبَنْتُ الشَّيْءَ: خَبَأْتُه في المَغْبِن.\nوشَيْءٌ غَبِنٌ: ضَعِيْفٌ قَليلٌ (¬١٦).\nوغَبَنْتُ السِّقَاءَ والثَّوبَ: إذا جَعَلْتَ فيه غُبُوناً أي أثْناءً، الواحِدُ غَبْنٌ.\n\n(¬١٧) غبن:\nالغَبَنُ في الرَّأْي: الفائلُ (¬١٣)، وكذلك في البَيْع، غَبنْتُه (¬١٤) فهو مَغْبُونٌ.\nوالفاتِرُ عن العَمَل: غابِنٌ. والغَبِيْنَةُ: الغَبْنُ.\nو ﴿يَوْمُ التَّغابُنِ﴾ في الآخِرَةِ بالأعمال (¬١٥).\nوالغَبْنُ في الثَّوْبِ: كالعَطْفِ.\nوغَبِنْتُ الرَّجُلَ أغْبَنُه: إذا أغْفَلْتَه.\nوالمَغابِنُ: الأرْفاغُ والآباطُ، الواحِدُ مَغْبِنٌ. واغْتَبَنْتُ الشَّيْءَ: خَبَأْتُه في المَغْبِن.\nوشَيْءٌ غَبِنٌ: ضَعِيْفٌ قَليلٌ (¬١٦).\nوغَبَنْتُ السِّقَاءَ والثَّوبَ: إذا جَعَلْتَ فيه غُبُوناً أي أثْناءً، الواحِدُ غَبْنٌ.\n\n(¬١٧)\nغنم:",
    "pg": "5:93"
  },
  "غبو": {
    "def": "غَبِيَ [فلانٌ] (¬١) غَبَاوَةً؛ فهو غَبٍ (¬٢): لا يَفْطنُ.\nوالغَبْوُ: بَذْرُ الحَبِّ، غَبَوْتُ الحَبَّ أغْبُوه. والتُّرَاب إذا ذَرَوْتَهُ.\nوالغَبَاءُ: الهَبَاءُ.\nويقولون (¬٣): «لا آتيكَ ما غَبَا غُبَيْسٌ» أي الدَّهْرَ. (و. ا. ي)\nغبو:\nغَبِيَ [فلانٌ] (¬١) غَبَاوَةً؛ فهو غَبٍ (¬٢): لا يَفْطنُ.\nوالغَبْوُ: بَذْرُ الحَبِّ، غَبَوْتُ الحَبَّ أغْبُوه. والتُّرَاب إذا ذَرَوْتَهُ.\nوالغَبَاءُ: الهَبَاءُ.\nويقولون (¬٣): «لا آتيكَ ما غَبَا غُبَيْسٌ» أي الدَّهْرَ.\nغبى:",
    "pg": "5:140"
  },
  "غبى": {
    "def": "الغَبْيَةُ: المَطْرَةُ المُتَتابِعَةُ القَطْرِ.\nوالغِبَاءُ (¬٤): التُّرَابُ الذي يُجْعَلُ فوقَ الغِطاءِ يُوَارِيه (¬٥). وغَبَّيْتُ مَجْرى الماءِ تَغْبِيَةً.\nوالمُغَبّاةُ: المَغَوّاةُ. والغَبَاءُ: الخَفَاءُ من الأرض. وما يَخْفى عنكَ.\nوغَبِّ شَعرَكَ: أي اسْتَأْصِلْه.\nوغب:",
    "pg": "5:140-141"
  },
  "غتم": {
    "def": "الغُتْمَةُ: عُجْمَةٌ (¬١٦) في المنطق. والأغْتَمُ: الذي لا يُفْصِحُ [/١٤٦ ب] شَيْئاً، وهو الغُتْمِيُّ.\nوالغَتْمُ: شِدَّةُ الحَرِّ والأخْذُ بالنَّفس.\nواغْتَتَمَ: أي (¬١٧) اتَّخَمَ.\nواسْمُ المَوْتِ: غُتَيْمٌ، و (¬١٨) يقولون (¬١٩): «وَرَدَ حِياضَ غُتَيْمٍ».\nتغم (¬٢٠):\nطَعامٌ مَتْغَمَةٌ: مَتْخَمَةٌ (¬٢١)، وأتْغَمَني الطَّعامُ. غمت:",
    "pg": "5:49-50"
  },
  "غثر": {
    "def": "الأغْثَرُ والغَثْرَاءُ من الأكْسِيَة: ما كَثُرَ صُوفُه وزِئْبِرُه، وبه يُشَبَّهُ الغَلْفَقُ.\nوالأغْثَرُ: من طَيْرِ الماء؛ مُلْتَبِسُ الرِّيشِ طَوِيلُ العُنُقِ.\nوالغَثْراءُ: سَفِلَةُ الناسِ.\nوالغَيْثَرَةُ: الجَماعَةُ المُخْتَلِطُونَ إذا أقْبَلُوا.\nوتَرَكْتُهم في غَيْثَرَةٍ: أي في قِتالٍ واضْطِرابٍ.\nوالغَيْثَرَةُ: الوَعِيدُ والتَّهَدُّدُ.\nوغُوْثِرَ بِبَني فلانٍ (¬٣) وغِيْثِرَ: أخَذوا منهم وتَرَكُوا.\nوالغَيْثَرَة (¬٤) -أيضاً-في الرَّأْسِ: ضُفُوُّ (¬٥) شَعرِه وكَثْرَتُه.\nوغَثَرَتِ الأرضُ بالنَّبات فهي مُغَثْرِيَةٌ: إذا مادَتْ بالنبات.\nووَجَدْتُ الماءَ مُغَثْرِياً بالوِرْدِ: إذا كانَ مَكْثُوراً عليه.\nوالغَثْرَةُ: الخِصْبُ والسَّعَةُ. واغْثَارَّ ثَوْبُكَ: أي كَثُرَ غَثَرُه أي زِئْبِرُه (¬٦).\nوالغَثْرَاءُ (¬٧): الضَّبُعُ، وكذلك غَثَارِ.\nويُقال للمَغافِير: مَغاثِيرُ.\nوالغَثْرَاءُ: الكَثيرةُ الشَّجَرِ (¬٨) واليَبِيْسِ والناسِ.\nثغر:",
    "pg": "5:55-56"
  },
  "غثم": {
    "def": "مُهْمَلٌ (¬٦٠).\nالخارزنجيُّ: إذا غَلَبَ بَيَاضُ شَعرِ الرَّأْسِ سَوَادَه فهو أغْثَمُ. وكذلك من الجِبالِ.\nونَبْتٌ مَغْثُومٌ: أي (¬٦١) مُخَلَّطٌ ليس بِجَيِّدٍ.\nوتَرَكْتُ القَوْمَ في غَيْثَمَةٍ: أي في قتالٍ واضْطِرابٍ.\nوغَثَمَ له وقَثَمَ: أعْطاهُ دُفْعَةً من المال.\nوالغَثِيْمَةُ (¬٦٢): طَعامٌ يُطْبَخُ ويُجْعَل فيه جَرَادٌ. غرل:",
    "pg": "5:62-63"
  },
  "غثى": {
    "def": "الغَثى: الغَثَيَانُ وهو خُبْثُ النَّفْسِ، غَثَتْ نَفْسُه تَغْثي (¬١) غَثْياً.\nوالغُثَاءُ: ما جاءَ به السَّيْلُ من نَباتٍ قد يَبِسَ. [و] (¬٢) يُقال: غَثَا الوادي يَغْثُو غُثُوّاً (¬٣): صارَ فيه الغُثَاءُ.\nوغَثَيْتُ الكلامَ أغْثَاهُ وأغْثِيه: أي خَلَطْتَه.\nوغَثَيْتُ المالَ والناسَ أغْثِيْهم: إذا خَبَطْتَهم وضَرَبْتَ فيهم (¬٤).\nوغَثَأْتُ الكلامَ أيضاً.\nوغَثِيَتِ الأرضُ بالنَّبات: كَثُرَتْ (¬٥). (و. ا. ي)\nغثى:\nالغَثى: الغَثَيَانُ وهو خُبْثُ النَّفْسِ، غَثَتْ نَفْسُه تَغْثي (¬١) غَثْياً.\nوالغُثَاءُ: ما جاءَ به السَّيْلُ من نَباتٍ قد يَبِسَ. [و] (¬٢) يُقال: غَثَا الوادي يَغْثُو غُثُوّاً (¬٣): صارَ فيه الغُثَاءُ.\nوغَثَيْتُ الكلامَ أغْثَاهُ وأغْثِيه: أي خَلَطْتَه.\nوغَثَيْتُ المالَ والناسَ أغْثِيْهم: إذا خَبَطْتَهم وضَرَبْتَ فيهم (¬٤).\nوغَثَأْتُ الكلامَ أيضاً.\nوغَثِيَتِ الأرضُ بالنَّبات: كَثُرَتْ (¬٥).\nثغو:",
    "pg": "5:119"
  },
  "غدب": {
    "def": "مُهْمَلٌ عنده (¬٦٦).\nالخارزنجيُّ: رَجُلٌ غُدُبَّةٌ: أي غَليظٌ كثيرُ العَضَلِ.\nوالغُدْبَةُ: لَحْمَةٌ (¬٦٧) غليظةٌ في اللَّهازِم.\nبغد والدَّغْفُ: الأخْذُ الكثير (¬٦٢).\n\n\nبدغ:\nالبَدْغُ: التَّزَحُّفُ بالاسْتِ على الأرض.\nوبَدِغَتِ (¬٦٣) الناقَةُ: أي سَمِنَتْ فَثَقُلَتْ (¬٦٤). والبَدَغُ: السِّمَنُ.\nوالبَدْغُ: الخَرْءُ، وهو بَدِغٌ بخرئه.\nدبغ:\nالدَّبْغُ (¬٦٥): مَصْدَرُ قَولِكَ دَبَغْتُ الجِلْدَ. والدِّبَاغُ: الاسْمُ.\nغدب:\nمُهْمَلٌ عنده (¬٦٦).\nالخارزنجيُّ: رَجُلٌ غُدُبَّةٌ: أي غَليظٌ كثيرُ العَضَلِ.\nوالغُدْبَةُ: لَحْمَةٌ (¬٦٧) غليظةٌ في اللَّهازِم.\nبغد\n(¬٦٨):",
    "pg": "5:44"
  },
  "غدف": {
    "def": "الغِدْفَةُ: لِباسُ المُلْكِ. والدُّجى. وأشباهُهما حتّى الغُرْلَة (¬٥٠).\nوالإِغْدَافُ: إرْسالُ القِناعِ على الوَجْه.\nوأغْدَفَ اللَّيْلُ واغْدَوْدَف: [إذا] (¬٥١) أرْخى سُدُوْلَه.\nوالغُدَافُ: غُرابٌ ضَخْمٌ وافِرُ الجَناحَيْنِ.\nوالشَّعرُ الطَّويلُ الأسودُ (¬٥٢): غُدَافٌ.\nوأُغْدِفَ في خِتانِ الصَّبِيِّ: أي اسْتُؤْصِل (¬٥٣).\nوالقَوْمُ في غَدَفٍ من عَيْشِهم: أي خِصْب.\nوغَدَفَ فلانٌ للناسِ في العَطاءِ. واغْتَدَفُوا: أي أخَذوا كثيراً منه. وغُدَافُ (¬٥٤): اسْمُ رَجُلٍ.\nوأُغْدِفَ بالصَّيْدِ: إذا أُلْقِيَ عليه الشَّبَكَةُ فَيُصْطاد.\nوأغْدَفَ الرَّجُلُ بالمَرْأةِ: إذا (¬٥٥) جامَعَها.\nوالغِدَفُّ: الأسَدُ.\nفدغ\n(¬٥٦):",
    "pg": "5:42-43"
  },
  "غدل": {
    "def": "مُهْمَلٌ عنده (¬٤٢).\nالخارزنجيُّ (¬٤٣): عَيْشٌ غَيْدَلٌ: [أي] (¬٤٤) ناعِمٌ. غدل:\nمُهْمَلٌ عنده (¬٤٢).\nالخارزنجيُّ (¬٤٣): عَيْشٌ غَيْدَلٌ: [أي] (¬٤٤) ناعِمٌ.\n\n\nغدن:",
    "pg": "5:41"
  },
  "غدن": {
    "def": "المُغْدَوْدِنُ: الشَّعرُ الكثيرُ المُلْتَفُّ.\nورَجُلٌ مُغْدَوْدِنٌ: لَيِّنٌ في كلامِه.\nوالغَدَنُ: الاسْتِرخاءُ والفَتْرَةُ. وهو النَّوْمُ. والنُّعَاسُ أيضاً.\nوإنَّ فيه لَغَدَناً: أي لِيْناً ونَعْمَةً.\nوالغَدَوْدَنيُّ: السَّرِيع.\nوالمُغْدَوْدِنُ: الناعِمُ.\nوالشابُّ الغُدَانيُّ: الذي امْتَلأَ شَباباً. غدل:\nمُهْمَلٌ عنده (¬٤٢).\nالخارزنجيُّ (¬٤٣): عَيْشٌ غَيْدَلٌ: [أي] (¬٤٤) ناعِمٌ.\n\n\nغدن:\nالمُغْدَوْدِنُ: الشَّعرُ الكثيرُ المُلْتَفُّ.\nورَجُلٌ مُغْدَوْدِنٌ: لَيِّنٌ في كلامِه.\nوالغَدَنُ: الاسْتِرخاءُ والفَتْرَةُ. وهو النَّوْمُ. والنُّعَاسُ أيضاً.\nوإنَّ فيه لَغَدَناً: أي لِيْناً ونَعْمَةً.\nوالغَدَوْدَنيُّ: السَّرِيع.\nوالمُغْدَوْدِنُ: الناعِمُ.\nوالشابُّ الغُدَانيُّ: الذي امْتَلأَ شَباباً.\nدغن:",
    "pg": "5:41"
  },
  "غدو": {
    "def": "غَدا يَغْدُو غُدُوّاً، واغْتَدى يَغْتَدي (¬٥) اغْتِداءً.\nوالغُدى: جَمْعُ غُدْوَةٍ، والغُدُوُّ: جَمْعُ غَدَاةٍ.\nوالغَدَاءُ: معروفٌ. ورَجُلٌ غَدْيانٌ؛ وامْرَأةٌ غَدْيَا، وغَدْوانٌ أيضاً (¬٦). وغَدِيَ الرَّجُلُ: تَغَدّى.\nوالغادِيَةُ: سَحابَةٌ تَنْشَأُ صَبَاحاً (¬٧)، والجميع الغَوادي.\nوالغَدَوِيُّ: كلُّ ما في بُطُونِ الحَوامِل، ومنهم مَنْ يَجْعَلُه في الشّاءِ (¬٨) خاصَّةً.\nوغَدٌ: اسْمٌ ناقِصٌ، يقولون: غَدا غَدُكَ (¬٩) وغَدا غَدْوُكَ. والأغْيَدُ: الوَسنانُ المائلُ العُنُقِ. وهو يَتَغايَدُ في مَشْيِه.\nوإنّه لَفي غَيْدانِ شَبابِه: أي حِدْثانِه.\nغدو:\nغَدا يَغْدُو غُدُوّاً، واغْتَدى يَغْتَدي (¬٥) اغْتِداءً.\nوالغُدى: جَمْعُ غُدْوَةٍ، والغُدُوُّ: جَمْعُ غَدَاةٍ.\nوالغَدَاءُ: معروفٌ. ورَجُلٌ غَدْيانٌ؛ وامْرَأةٌ غَدْيَا، وغَدْوانٌ أيضاً (¬٦). وغَدِيَ الرَّجُلُ: تَغَدّى.\nوالغادِيَةُ: سَحابَةٌ تَنْشَأُ صَبَاحاً (¬٧)، والجميع الغَوادي.\nوالغَدَوِيُّ: كلُّ ما في بُطُونِ الحَوامِل، ومنهم مَنْ يَجْعَلُه في الشّاءِ (¬٨) خاصَّةً.\nوغَدٌ: اسْمٌ ناقِصٌ، يقولون: غَدا غَدُكَ (¬٩) وغَدا غَدْوُكَ.\nدغو:",
    "pg": "5:114"
  },
  "غذم": {
    "def": "الغَذْمُ: الأكْلُ بحَقْرٍ (¬٢٠) وشِدَّةِ نَهَمٍ، ورَجُلٌ غُذَمٌ.\nوغَذَمَ ما في ضَرْعِه وغَنْذَمَه: أي لم يُبْقِ فيه شَيْئاً، واغْتَذَمَه كذلك.\nوالغَذَمُ (¬٢١): الكَثيرُ من اللَّبَنِ، الواحِدةُ غَذَمَةٌ.\nوأصابَ من مَعْروفِه غُذْمَةً (¬٢٢) بعد غُذْمَةٍ: أي شَيْئاً بَعْدَ شَيْءٍ.\nوكَيْلٌ غَذَمْذَمٌ وغَذِمٌ وسَيْلٌ كذلك: أي كثيرٌ.\nوالغَذائمُ: البُحُور، واحِدُها (¬٢٣) غَذِيْمَةٌ.\nوالغَذِيْمَةُ: كُلُّ (¬٢٤) مُتَراكِمٍ (¬٢٥) بعضُه على بعضٍ.\nوبِئْرٌ غَذِمَةٌ (¬٢٦) و (¬٢٧) ذاتُ غَذِيمةٍ: أي كثيرةُ الماءِ.\nوغَذِيمةُ الرَّجُلِ: رَحَابَةُ ذَرْعِه وسَعَةُ خُلقِه. وأوَّلُ نَباتِ الأرضِ.\nوالغَذائمُ: قِطَعُ الكَلَإِ والعُشْبِ.\nوالغَذَمُ: نَبْتٌ.\nوجاءني مُتَغَذِّماً: قد امْتَلأَ من الغَضَب. (¬١)\n(¬٢)\nغثر:",
    "pg": "5:54-55"
  },
  "غذو": {
    "def": "الغِذَاءُ: الطَّعامُ وغيرُه، غَذَا يَغْذو غِذَاءً، وتَغَذّى (¬١) تَغَذِّياً.\nوالغَذَوانُ: النَّشِيْطُ من الخَيْل.\nواسْتَغْذى الرَّجُلُ صاحِبَه اسْتِغْذاءً: إذا صَرَعَه فَشَدَّ صَرْعَه. ومنه يُقال: قِرْبَةٌ تَغْذي (¬٢) بالماء: أي تَرْمي به وتَصُبُّه صَبّاً.\nوالغاذِيَةُ: عِرْقٌ.\nوفلانٌ غاذِيُّ مالٍ: أي مُصْلِحُها (¬٣)، كأنَّه يَغْذُوْها بالرَّعْي. (و. ا. ي) [/١٥١ أ]\nغذو:\nالغِذَاءُ: الطَّعامُ وغيرُه، غَذَا يَغْذو غِذَاءً، وتَغَذّى (¬١) تَغَذِّياً.\nوالغَذَوانُ: النَّشِيْطُ من الخَيْل.\nواسْتَغْذى الرَّجُلُ صاحِبَه اسْتِغْذاءً: إذا صَرَعَه فَشَدَّ صَرْعَه. ومنه يُقال: قِرْبَةٌ تَغْذي (¬٢) بالماء: أي تَرْمي به وتَصُبُّه صَبّاً.\nوالغاذِيَةُ: عِرْقٌ.\nوفلانٌ غاذِيُّ مالٍ: أي مُصْلِحُها (¬٣)، كأنَّه يَغْذُوْها بالرَّعْي.\nغيذ:",
    "pg": "5:118"
  },
  "غرب": {
    "def": "الغَرْبُ: التَّمادي والحِدَّةُ: وجِلْدُ تامٌّ يُتَّخَذُ منه دَلْوٌ. وكُلُّ فَيْضَةٍ من الدَّمع غَرْبٌ، وجَمْعُه غُرُوبٌ. وداءٌ وخُرّاجٌ في العَيْن. ومَغْرِبُ الشَّمْسِ. والفَرَسُ الحَدِيدُ. والسَّيْفُ القاطِعُ.\nوأغْرَبَ واسْتَغْرَبَ الرَّجُلُ: لَجَّ في الضّحكِ خاصَّةً.\nواسْتَغْرَبَ عليه: اشْتَدَّ غَضَبُه.\nوالغَرَبُ: ماءٌ يَقْطُرُ من الدِّلاء فَيَتَغَيَّر رِيْحُه. وأغْرَبَ الساقي:\nإذا (¬٦٢) أكْثَرَ الغَرَبَ. وأغْرَبَ الحَوْضُ: فاضَتْ جَوانِبُه، وكذلك الكأْسُ فهي مُغْرِبَةٌ.\nوغُرُوْبُ الأسنانِ: أطرافُها.\nوالغُرُوْبُ: غَيْبُوبَةُ الشَّمْسِ، وكذلك المُغَيْرِبَانُ. وأتانا عند غِرِبّانِ (¬٦٣) الشَّمسِ ومُغَيْرِباناتِها (¬٦٤).\nوالغُرْبَةُ: الاغْتِرابُ من الوَطَنِ.\nوالغُرْبُ: الذَّهَابُ والتَّنَحّي عن الناسِ، غَرَبَ غُرْباً. وأغْرَبْتُه وغَرَّبْتُه: إذا نَحَّيْتَه، وأغْرِبْهُ وغَرِّبْهُ. وفي المَثَل (¬٦٥): «أكْذَبُ من شَيْخٍ غَرِيبٍ».\nوالغُرْبَةُ: النَّوى والبُعْدُ. وأغْرَبَ القَوْمُ: انْتَوَوْا. وغايَةٌ مُغَرِّبَةٌ: بَعِيدةٌ.\nوالكِلابُ إذا أمْعَنَتْ في طَلَبِ الصَّيْدِ قيل: غَرَّبَتْ. وَبَلَدٌ مُغَرِّبٌ وغُرَّبٌ (¬٦٦): بَعِيْدٌ.\nوغَرَّبَ الرَّجُلُ تَغْرِيباً: بَعُدَ. وهل من مُغَرِّبَةٍ خَبَرٌ: أي خَبَرٌ طَرأَ عليك. وشَأْوٌ مُغَرِّبٌ.\nوأغْرَبَ الرَّجُلُ في مَنْطِقِه: إذا لم يُبْقِ شَيْئاً إلاّ تَكَلَّمَ به، والفَرَسُ في جَرْيِه. والغَرِيْبُ من الكلام: الغامِضُ، غَرُبَتِ الكلمةُ تَغْرُبُ غَرَابَةً، وصاحِبُها مُغْرِبٌ.\nوالغارِبُ: أعْلى المَوْجِ والظَّهْرِ. ويقولون للمَرْأةِ عند الطَّلاقِ: حَبْلُكِ على غارِبِكِ.\nوالمُغْرَبُ: الأبْيَضُ الأشْفارِ من كلِّ صِنْفٍ.\nوالعَنْقَاءُ المُغْرِبُ والمُغْرِبَةُ، وإغْرَابُها: غَرْبُها في طَيَرانِها. وقيل العَنْقاءُ المُغْرِبُ: هي رَأْسُ الأكَمَةِ في أعْلى الجَبَلِ الطَّويلِ.\nوالبَرَدُ يُسَمّى غَرَباً (¬٦٧)؛ لبَياضِه. والصُّبْحُ مُغْرَبٌ. ورَجُلٌ مُغَرَّبٌ (¬٦٨):\nيَبْيَضُّ شَعرُ رَأْسِه ولِحْيَتِه، وفَرَسٌ كذلك: إذا اتَّسَعَتْ غُرَّتُه في وَجْهِه.\nوالغُرَابُ: طائرٌ، والجميع غِرْبانٌ (¬٦٩) وأغْرِبَةٌ، وهذه غِرْبَنَّةٌ وغُرَابَةٌ للأُنْثى، والذَّكَرُ غِرْبَنٌّ.\nوالغُرَابانِ: نُقْرَتانِ عند الصَّلَوَيْنِ في العَجُز، وجَمْعُه غِرْبانٌ.\nوالغُرَابُ: ما يُعْقَدُ من الدَّلْوِ إلى الصُّلْب.\nورِجْلُ الغُرَابِ: نَوْعٌ من الصِّرَار في خِلْفِ الناقَةِ، وإذا اشْتَدَّ على الرَّجُلِ الأمْرُ وضاقَ عليه قِيْلَ (¬٧٠): صُرَّ عليه رِجْلُ الغُرَاب (¬٧١). وهو-أيضاً-: ضَرْبٌ من النَّبت.\nوالغَرْبيُّ من الشَّجَرِ: الذي تُصِيبُه الشَّمْسُ بحَرِّها عند الأُفُول. وصِبْغٌ أحْمَرُ. والفَضِيْخُ من النَّبِيْذ. والغَرَبُ: شَجَرٌ يُتَّخَذُ منه الأقداحُ. وجامٌ من فِضَّة. وموضعٌ يَسِيلُ فيه (¬٧٢) الماءُ بين البِئْرِ والحَوْض. والخَمْرُ.\nوالغِرْبِيْبُ (¬٧٣): الأسْوَدُ، وكذلك الغِرْبابُ (¬٧٤).\nويُقال لعَناقِيدِ البَرِيْرِ: غِرْبانُ البَرِيْرِ؛ لسَوادِها.\nوالغُرَابِيَّةُ: نَخْلةٌ بالبَصْرَةِ (¬٧٥).\nوسَهْمٌ غَرْبٌ: لا يُعْرَفُ رامِيْه.\nوالمُغْرَبُ (¬٧٦): الثَّغْرُ الذي فيه حِدَّةٌ وشَنَبٌ.\nوذِرَاعٌ غَرَبٌ: أي (¬٧٧) طَويلةٌ.\nوغَرِبَتِ العَيْنُ تَغْرَبُ غَرَباً: إذا كانَ بها وَرَمٌ في المَأْقِ.\nوفَرَسٌ غَرِبٌ: من الغَرَبِ؛ وهو عِرْقٌ يَسْقي و (¬٧٨) لا يَبْرَأُ من دَبَرَتِه أبداً.\nوهو-أيضاً-: شِبْهُ الجَرَبِ، شاةٌ غَرِبَةٌ، وإهَابٌ غَرِبٌ، وغَنَمٌ غَرْبى، وإبلٌ غَرَابى (¬٧٩)، وأُغْرِبَتْ فهيَ مُغْرَبَةٌ.\nوهو في إغْرَابٍ من العَيْش: أي في سَعَةٍ.\nوأُغْرِبَ الرَّجُلُ: اشْتَدَّ وَجَعُه من مَرَضٍ أو غيرِه.\nوالغَرَايِبُ: العَرايِسُ، واحِدُها غَرْبِيَةٌ (¬٨٠). رغب:",
    "pg": "5:71-75"
  },
  "غرث": {
    "def": "الغَرَثُ: الجُوْعُ، والنَّعْتُ غَرْثانُ وغَرْثى وغَرَاثِيْنُ.\nوجارِيَةٌ غَرْثى (¬١٦) الوِشَاحِ. رغث:",
    "pg": "5:56-57"
  },
  "غرد": {
    "def": "كلُّ صائتٍ طَرِب (¬٢٧) الصَّوْتِ: غَرِدٌ. و (¬٢٨) غَرَّدَ الطائرُ تَغْريداً.\nوالغِرَادُ: الكَمْأةُ الرَّديئة، الواحدة غَرْدَةٌ وغِرْدٌ، وهي الغِرَدَةُ أيضاً، وهي المَغارِيْدُ. ومَغْرُوْدَاءُ: أرضٌ ذاتُ مَغارِيْد.\nوالغَرْدُ: الجِصُّ (¬٢٩). رغد:",
    "pg": "5:38-39"
  },
  "غرز": {
    "def": "الغَرْزُ: غَرْزُكَ إبْرَةً في شَيْءٍ. ورِكَابُ الرَّجُل (¬٣)، و (¬٤) كُلُّ ما كانَ مَسَاكاً للرِّجْلَيْنِ في المركَبِ سُمِّيَ: غَرْزاً.\nوجَرَادَةٌ غارِزٌ وغارِزَةٌ: إذا رَزَّتْ ذَنَبَها في الأرض لِتَسْرَأَ.\nومَغْرِزُ الأضلاع: مُرَكَّبُ أُصُولها. وكذلك مَغَارِزُ الرِّيشِ ونحوِه.\nوالغَرِيْزَةُ: الطَّبِيعةُ من خُلُقٍ صالِحٍ أو رَديءٍ.\nوغَرَزَتِ الناقَةُ غِرَازاً (¬٥)؛ فهي غارِزٌ: قليلةُ اللَّبَنِ. وغَرَّزَها صاحبُها: إذا تَرَكَ حَلَبَها لِيَذْهَبَ رِفْدُها.\nوضَرْبٌ من الثُّمَام من أصْغَرِه يُسَمّى: الغَرَزَ، الواحدة غَرَزَةٌ. ووادٍ مُغْرِزٌ:\nبه الغَرَزُ.\nوالغُرُوْزُ: الأغصانُ التي تُغْرَزُ (¬٦) في قُضبْان الكَرْمِ للوَصْل. رغز (¬٧):\nاسْتَرْغَزَه -بمعنى السِّين (¬٨) -: [أي] (¬٩) اسْتَضْعَفه واسْتلانَه.\nرزغ:",
    "pg": "5:23-24"
  },
  "غرس": {
    "def": "الغِرَاسُ: وَقْتُ الغَرْسِ، والمَغْرِسُ: مَوْضِعُه.\nوالغِرَاس (¬٨) -أيضاً-: فَسِيْلُ النَّخْل.\nوالغَرْسُ: الشَّجَرُ الذي يُغْرَسُ، وجَمْعُه أغراس.\nوالغَرِيْسُ: بِنْتُ النَّخلةِ الصَّفيّ.\nوالغِرْسُ: جُلَيْدَةٌ رَقِيقةٌ تخرج على رَأْسِ الوَلَدِ إذا مُسَّت انْمَاثَتْ.\nويقولون: نَحْنُ في مَغْرُوسَةٍ من الأمْرِ-بمعنى مَرْغُوسَةٍ-: أي في اخْتِلاطٍ.\nوتُسَمّى النَّعْجَةُ: الغَرِيْسَ. وتُدْعى للحَلبِ فيُقال: غَرِيْس غَرِيْس (¬٩). ويُقال للفَحْل إذا ضَرَبَ الناقةَ على غَيْرِ ضَبَعَةٍ: غَسَرَها، وهو القَسْرُ (¬٧).\nغرس:\nالغِرَاسُ: وَقْتُ الغَرْسِ، والمَغْرِسُ: مَوْضِعُه.\nوالغِرَاس (¬٨) -أيضاً-: فَسِيْلُ النَّخْل.\nوالغَرْسُ: الشَّجَرُ الذي يُغْرَسُ، وجَمْعُه أغراس.\nوالغَرِيْسُ: بِنْتُ النَّخلةِ الصَّفيّ.\nوالغِرْسُ: جُلَيْدَةٌ رَقِيقةٌ تخرج على رَأْسِ الوَلَدِ إذا مُسَّت انْمَاثَتْ.\nويقولون: نَحْنُ في مَغْرُوسَةٍ من الأمْرِ-بمعنى مَرْغُوسَةٍ-: أي في اخْتِلاطٍ.\nوتُسَمّى النَّعْجَةُ: الغَرِيْسَ. وتُدْعى للحَلبِ فيُقال: غَرِيْس غَرِيْس (¬٩).\nرغس:",
    "pg": "5:13"
  },
  "غرف": {
    "def": "الغَرْفُ: غَرْفُكَ الماءَ باليَدِ وبالمِغْرَفَة. والغُرْفَةُ: قَدْرُ اغْتِرافَةٍ مِلْءَ الكَفِّ.\nوالغَرْفَةُ: مَرَّةٌ واحِدَةٌ. وغَرْبٌ غَرُوْفٌ (¬٣٠): كبيرٌ. ومَزَادَةٌ غَرْفِيَّةٌ، وهي-أيضاً-:\nالمَدْبُوغَةُ بالغَرَفِ.\nوالغَرِيْفَةُ: كُلُّ جِلْدَةٍ مَدْبُوغةٍ بالغَرَف.\nوغَرِفَتِ الإِبلُ: اشْتَكَتْ من أكْلِه.\nوالغَرِيْفُ: ماءٌ في أجَمَةٍ.\nوالغُرْفَةُ: العُلِّيَّةُ. والسَّماءُ السابِعَةُ: غُرْفَةٌ.\nوغَرَفْتُ ناصِيَةَ الفَرَسِ أغْرِفُها غَرْفاً: إذا جَزَزْتَها.\nوانْغَرَفَ عَظْمُه: انْكَسَرَ.\nوالغَرِيْفَةُ: النَّعْلُ. وهي-أيضاً-: جِلْدَةٌ من أدَمٍ في أسْفَلِ قِرَابِ السَّيْفِ.\nوالغَرْفُ: شَجَرٌ.\nوالغَرَفُ -على وَزْنِ مَطَرٍ-: شَجَرُ القِسِيِّ.\nوالغَرِيْفَةُ: شَجَرُ البانِ (¬٣١).\nوالغُرفَةُ (¬٣٢): الحَبْلُ المَعْقُودُ بأُنْشُوطَةٍ، غَرَفْتُ البَعِيرَ أغْرِفُهُ غَرْفاً: إذا ألْقَيْتَ في رأْسِه ذاكَ.\nويُقال: تَغَرَّفْتُموني: إذا أخَذُوا كُلَّ شَيْءٍ.\nوالغِرْيَفُ: شَجَرُ البانِ-على وَزْنِ حِذْيَمٍ- (¬٣٣).\nقال الصاحِبُ: الصَّحيحُ في الغَرَفِ فَتْحُ الراء، كذا وَجَدْتُه في أصْلِ أبي حَنِيفَةَ بخَطِّه، والواحِدَةُ غَرَفَةٌ (¬٣٤).\nوالغَرَفُ: الثُّمَامُ، عن أبي عمرو. ويُقال: الغَرَفُ من شَجَرِ الرَّمْلِ (¬٣٥).\nفغر:",
    "pg": "5:66-67"
  },
  "غرل": {
    "def": "الغَرَلُ: القَلَفُ. والغُرْلَةُ: القُلْفَةُ. [والأغْرَلُ] (¬١) والجميع الغُرْلُ.\nوالمُسْتَرْخي (¬٢) الخَلْقِ: غَرِلٌ.\nوالغِرْيَلُ (¬٣): الغُبَارُ. ومُخَاطُ (¬٤) كُلِّ ذي حافِرٍ. وزَبَدُ أفْواهِ الدَّوابِّ إذا اخْتَلَطَ (¬٥) بالماء. وما يبقى في الحَوْضِ من الماء. غرل:\nالغَرَلُ: القَلَفُ. والغُرْلَةُ: القُلْفَةُ. [والأغْرَلُ] (¬١) والجميع الغُرْلُ.\nوالمُسْتَرْخي (¬٢) الخَلْقِ: غَرِلٌ.\nوالغِرْيَلُ (¬٣): الغُبَارُ. ومُخَاطُ (¬٤) كُلِّ ذي حافِرٍ. وزَبَدُ أفْواهِ الدَّوابِّ إذا اخْتَلَطَ (¬٥) بالماء. وما يبقى في الحَوْضِ من الماء.\nرغل:",
    "pg": "5:63"
  },
  "غرم": {
    "def": "الغُرْمُ: أدَاءُ شَيْءٍ لَزِمَه، غَرِمْتُه أغْرَمُه. والغَرِيمانِ: الغارِمُ والمُغَرِّم.\nوالغَرَامُ: العَذَابُ. والشَّرُّ اللازِمُ. وثِقَلٌ لا تَفَصِّيَ (¬١٤٥) منه. وشاةٌ رَغْمَاءُ: على طَرَفِ أنْفِها بَيَاضٌ.\nوالرَّغَامُ [/١٤٩ أ]: زَبَدُ الماءِ يَرْمي به السَّيْلُ.\nو ﴿مُراغَماً كَثِيراً وَسَعَةً﴾ (¬١٤٣) أي مُتَّسَعاً لِهجْرَتِه.\nوالمُرْغِمَةُ (¬١٤٤): لُعْبَةٌ.\nولي عند فلانٍ رُغَامَةٌ: أي طَلِبَةٌ ومَغْضَبٌ.\nوفلانٌ لا يُرَاغِمُ شَيْئاً: أي لا يُعْوِزُه شَيْءٌ.\nوالمُتَرَغَّمُ: المَذْهَبُ والمُضْطَرَبُ، ومِثْلُه المَرْغَمُ.\nغرم:\nالغُرْمُ: أدَاءُ شَيْءٍ لَزِمَه، غَرِمْتُه أغْرَمُه. والغَرِيمانِ: الغارِمُ والمُغَرِّم.\nوالغَرَامُ: العَذَابُ. والشَّرُّ اللازِمُ. وثِقَلٌ لا تَفَصِّيَ (¬١٤٥) منه.\nرمغ:",
    "pg": "5:82"
  },
  "غرن": {
    "def": "مُهْمَلٌ (¬٢٣).\nالخارزنجيُّ: الغَرَنُ [/١٤٧ ب]: السَّرَطانُ، وقيل: ذَكَرُ العِقْبانِ، وجَمْعُه أغْرَانٌ (¬٢٤).\nوالغَرِنُ: الضَّعِيفُ.\nوالغِرْيَنُ: الطِّينُ الرَّقيقُ في أسْفَلِ الحَوْض، ويُشَدَّدُ النُّونُ منه. وهو الحُمْقُ أيضاً، من قَوْلهم: رَماني بِغِرْيَنِه: أي بحُمْقِه. وهو يَرْمي عَلَيَّ بالغِرْيَنِ: أي بالزَّبَدِ من الغَضَب.\nوما طَفا فَوْقَ الماء من زَبَدٍ أو غُثَاءٍ (¬٢٥): غِرْيَنٌ.\nوإذا يَبِسَ العَجِينُ على القَرْوِ قيل (¬٢٦): [قد] (¬٢٧) غَرِنَ.\n\n\nرغف:",
    "pg": "5:65-66"
  },
  "غره": {
    "def": "الخارزنجيُّ: غَرِهَ بي يَغْرَهُ غَرَهاً: بمعنى غَرِيَ. غره:\nالخارزنجيُّ: غَرِهَ بي يَغْرَهُ غَرَهاً: بمعنى غَرِيَ.\n\n\nهلغ:",
    "pg": "3:335"
  },
  "غرو": {
    "def": "لا غَرْوَ: أي لا عَجَبَ. وإنَّ الصَّمْغَ لَيَغْرُو كَبِدي: أي يُعْجِبُها ويُصْلِحُها (¬١).\nوغَرَوْتُه أغْرُوْهُ: أي ألْزَقْته؛ من الغِرَاء (¬٢)؛ فانْغَرى. وأغْرَيْتُه أيضاً، وهو مُغْرىً و (¬٣) مُغَرّى.\nوغَرِيْتُ بكَذا: أُوْلِعْتَ به، وهو الغِرَاءُ (¬٤).\nوغَرَوْتُ السَّهْمَ. وفي المَثَلِ (¬٥): «أدْرِكْني ولو بأحَدِ المَغْرُوَّيْنِ» أي بأحَدِ السَّهْمَيْنِ.\nوالمَغْرُوُّ: المُلْصَقُ بالقَوْم.\nوالغَرا (¬٦): وَلَدُ البَقَرَةِ-مَقْصُورٌ-، وتَثْنِيَتُه غَرَوانِ. والغَرا: المَهْزُوْلُ، وجَمْعُه أغْرَاءُ، وكذلك الغَرَاةُ.\nوغَرَا اللَّهُ الأرْضَ يَغْرُوْها: أي مَطَرَهَا.\nوالغَرِيُّ: اسْمُ وَثَنٍ مَنْصُوبٍ.\nوالغَرِيّان (¬٧): مَوضِعٌ.\nغرى:",
    "pg": "5:122-123"
  },
  "غرى": {
    "def": "الإِغْرَاءُ: الإِنْشَاءُ (¬٨)، أغْرَيْتُ بينهم العَداوَةَ.\nوغارَيْتُ بَيْنَ اثْنَيْنِ: والَيْت [بينهما] (¬٩).\nوالمُغَاراةُ: المُلاجَّةُ (¬١٠)، وهُما يَتَغَارَيانِ (¬١١) في الغَضَبِ. والغَرا: المَهْزُوْلُ، وجَمْعُه أغْرَاءُ، وكذلك الغَرَاةُ.\nوغَرَا اللَّهُ الأرْضَ يَغْرُوْها: أي مَطَرَهَا.\nوالغَرِيُّ: اسْمُ وَثَنٍ مَنْصُوبٍ.\nوالغَرِيّان (¬٧): مَوضِعٌ.\nغرى:\nالإِغْرَاءُ: الإِنْشَاءُ (¬٨)، أغْرَيْتُ بينهم العَداوَةَ.\nوغارَيْتُ بَيْنَ اثْنَيْنِ: والَيْت [بينهما] (¬٩).\nوالمُغَاراةُ: المُلاجَّةُ (¬١٠)، وهُما يَتَغَارَيانِ (¬١١) في الغَضَبِ.\nغور:",
    "pg": "5:123"
  },
  "غزد": {
    "def": "الغِزْيَدُ: الشَّديدُ الصَّوْتِ. والناعِمُ من النَّبات. غزد:\nالغِزْيَدُ: الشَّديدُ الصَّوْتِ. والناعِمُ من النَّبات.\nزغد:",
    "pg": "5:22"
  },
  "غزر": {
    "def": "غَزُرَتِ الناقَةُ والشاةُ تَغْزُرُ غَزَارَةً، فهي غَزِيْرَةٌ: كثيرة اللَّبَنِ. وَعَيْنٌ غَزِيرةُ الماء.\nومَعْروفٌ غَزِيرٌ: مُتَتابعٌ.\nوأَنْتُم مُغْزَرٌ بكم ولكم: أي كثيرةٌ أموالُكم.\nوَأَغْزَرَ القَومُ إِغْزَاراً: غَزُرَتْ إبلُهم. غزر:\nغَزُرَتِ الناقَةُ والشاةُ تَغْزُرُ غَزَارَةً، فهي غَزِيْرَةٌ: كثيرة اللَّبَنِ. وَعَيْنٌ غَزِيرةُ الماء.\nومَعْروفٌ غَزِيرٌ: مُتَتابعٌ.\nوأَنْتُم مُغْزَرٌ بكم ولكم: أي كثيرةٌ أموالُكم.\nوَأَغْزَرَ القَومُ إِغْزَاراً: غَزُرَتْ إبلُهم.\nغرز:",
    "pg": "5:23"
  },
  "غزل": {
    "def": "غَزَلَتِ المَرْأةُ تَغْزِلُ. والمِغْزَلُ والمُغْزَل (¬٢٨): لُغَتانِ. وفي المَثَل (¬٢٩): «أضَلُّ من ساقِ مِغْزَلٍ» لأنَّه يَكْسُو الناسَ وهو عارٍ.\nوالغَزَلُ: حَدِيثُ الفِتيانِ [مع] (¬٣٠) الجَواري، غازَلَها مُغازَلةً. وفلانٌ غِزْلُ (¬٣١) نِساءٍ وغِزِّيْلُ (¬٣٢) نِساءٍ: أي تِبْعُهُنَّ (¬٣٣).\nوالغَزَالُ: الشادِنُ قَبْلَ الإِثْنَاءِ حين يَتَحَرَّكُ ويَمْشي (¬٣٤).\nوالغَزِلُ: الكَلْبُ الذي إذا أدْرَكَ الغَزَالَ تَرَكَه ولَهِيَ عنه.\nوالغِزْلَةُ: جَمْعُ الغَزَال.\nوالغَزَالَةُ: عَيْنُ الشَّمْسِ. ورَأْدُ الضُّحى.\nوالمَغازِلُ: عَمَدُ النَّوْرَج الذي (¬٣٥) يُدَاسُ به الكُدْسُ.\nودارَةُ الغُزَيِّل: في بَلْحَرْثِ بن رَبِيعة. نزغ:",
    "pg": "5:26-27"
  },
  "غزو": {
    "def": "غَزَوْتُ؛ وأنا أغْزو غَزْواً. ورَجُلٌ غَزَوِيَّةٌ: غَزّاء. والغَزِيُّ: جَمْعُ الغُزَاةِ، وكذلك الغُزّى. والمَغْزَاةُ: مَوضِعُ الغَزْوِ.\nوالمَغازي: المَناقِبُ والغَزَوات.\nوأغْزَتِ المَرْأةُ: غَزَا زَوْجُها؛ فهي مُغْزِيَةٌ (¬١).\nوأغْزَتِ الناقَةُ فهي مُغْزٍ: إذا عَسُرَ لِقاحُها. (و. ا. ي)\nغزو:\nغَزَوْتُ؛ وأنا أغْزو غَزْواً. ورَجُلٌ غَزَوِيَّةٌ: غَزّاء. والغَزِيُّ: جَمْعُ الغُزَاةِ، وكذلك الغُزّى. والمَغْزَاةُ: مَوضِعُ الغَزْوِ.\nوالمَغازي: المَناقِبُ والغَزَوات.\nوأغْزَتِ المَرْأةُ: غَزَا زَوْجُها؛ فهي مُغْزِيَةٌ (¬١).\nوأغْزَتِ الناقَةُ فهي مُغْزٍ: إذا عَسُرَ لِقاحُها.\nزيغ:",
    "pg": "5:109"
  },
  "غسر": {
    "def": "تَغَسَّرَ الغَزْلُ: الْتَبَسَ. ويُقال للفَحْل إذا ضَرَبَ الناقةَ على غَيْرِ ضَبَعَةٍ: غَسَرَها، وهو القَسْرُ (¬٧).\nغرس:",
    "pg": "5:12-13"
  },
  "غسل": {
    "def": "الغُسْلُ: معروفٌ، والمَصْدَرُ: الغَسْلُ.\nوالغُسْلُ: الماءُ أيضاً (¬١٦). والغَسُوْلُ: ما غَسَلْتَ به.\nوالغِسْلُ: الخِطْميُّ.\nوالغِسْلَةُ: آسٌ يُطَرّى بأفاوِيهِ الطِّيْبِ يُمْتَشَطُ به.\nوالمُغْتَسَل: مَوْضِع الاغْتِسال، وتصغيره مُغَيْسِلٌ [/١٤٤ أ]، والجميع المَغاسِلُ والمَغاسِيل.\nوغِسْلِيْنُ -فِعْلِين-: من غَسَلْتُ، وقيل: الحارُّ الشَّديد.\nوغَسَلَ الرَّجُلُ المَرْأةَ: إذا نَكَحَ فألَحَّ. والمِغْسَلُ: الذي لا يَكادُ يُلْقِحُ من كَثْرَة ضِرَابِه، وفَحْلٌ غُسَلَةٌ ومِغْسَلٌ وغَسِيْلٌ.\nوالغِسْلَةُ: قِلَّةُ البَيَاضِ على الإِنسانِ والمِلْح (¬١٧). والغَسُّوْلُ من الحَمْض: نَحْوُ الرِّمْثِ.\nوأبو غِسْلَةَ: كُنْيَةُ الذِّئب.\nسغل:",
    "pg": "5:14-15"
  },
  "غسم": {
    "def": "الغَسَمُ (¬٦١): اخْتِلاطُ الظُّلْمة. وأوَّلُ طُلوع الفَجْرِ (¬٦٢).\nوأغْسَمَ اللَّيلُ: مِثْلُ أغْسى.\nوالغَسَمُ: الهَبْوَةُ والغَبرةُ. غزد:",
    "pg": "5:21-22"
  },
  "غسن": {
    "def": "الغُسَنُ: شَعرُ العُرْفِ والناصِيَةِ، الواحدة غُسْنَةٌ. وفَرَسٌ ذو غُسَنٍ.\nوالرَّجُلُ الجَمِيلُ جِدّاً: غَسّانيٌّ.\nوغَسّانُ: ماءٌ بالمُشَلَّلِ مَنْ شَرِبَ منه من الأزْدِ قيل: غَسّانيّ.\nوفلانٌ على أغْسانِ أبيه: أي أخلاقِه.\nولستَ من غَسّانِه وغَيْسانِه (¬٢٩): أي [لَسْتَ] (¬٣٠) من رِجالِه.\nوكان ذلك في غَسّانِ شَبابِه: أي نَعْمَتِهِ واسْترخائه.\nوأغْسَانُ (¬٣١) الثِّيابِ: خُلْقانُها.\nوأغْسَانُ الرِّجالِ: لِئامُهم.\nوالغُسْنُ: الضَّعيفُ من الرِّجال.\nوغَسَنَ الشَّيْءَ: مَضَغَ. والغِسَانُ: رَهْطُ الصَّبِيِّ (¬٣٢).\nنسغ:",
    "pg": "5:16-17"
  },
  "غسى": {
    "def": "غَسَا (¬١) اللَّيْلُ وغَسِيَ: أظْلَمَ (¬٢)، وأغْسى أصْوَبُ، يَغْسى ويَغْسُو غُسُوّاً.\nوشَيْخٌ غاسٍ: طويلُ العُمْرِ (¬٣).\nوأغْساني اللَّيْلُ: ألْبَسَني ظَلامَه.\nوالغُسْيَانُ: جَمْعُ الغَسَى وهو الغُسُوُّ، وكذلك الإِغْسَاءُ.\nوالغَسَاةُ (¬٤): البَلَحُ، وجَمْعُها غَسىً (¬٥).\nوالغَسْوُ: النَّبِقُ، الواحدة غَسْوَةٌ.\nوالغاسي: الذي يَسْقُطُ من البُسْر وهو أخْضَرُ فَيَنْضَج [بعد ذلك] (¬٦). (و. ا. ي)\nغسى:\nغَسَا (¬١) اللَّيْلُ وغَسِيَ: أظْلَمَ (¬٢)، وأغْسى أصْوَبُ، يَغْسى ويَغْسُو غُسُوّاً.\nوشَيْخٌ غاسٍ: طويلُ العُمْرِ (¬٣).\nوأغْساني اللَّيْلُ: ألْبَسَني ظَلامَه.\nوالغُسْيَانُ: جَمْعُ الغَسَى وهو الغُسُوُّ، وكذلك الإِغْسَاءُ.\nوالغَسَاةُ (¬٤): البَلَحُ، وجَمْعُها غَسىً (¬٥).\nوالغَسْوُ: النَّبِقُ، الواحدة غَسْوَةٌ.\nوالغاسي: الذي يَسْقُطُ من البُسْر وهو أخْضَرُ فَيَنْضَج [بعد ذلك] (¬٦).\nسوغ:",
    "pg": "5:107"
  },
  "غشو": {
    "def": "الغَشَاوَةُ والغِشَاوَةُ: ما غَشّى القَلْبَ.\nوغاشِيَةُ الرَّحْلِ (¬١) والسَّيْفِ: غِطاؤه. والحَدِيدةُ التي فَوْقَ المُؤخّرَةِ.\nوالذين يَغْشَوْنَكَ ويَرْجُونَ فَضْلَكَ: غاشِيَةٌ. وهي القِيامَةُ أيضاً. وداءٌ في الجَوْفِ، رَمَاهُ اللَّهُ بغاشِيَةٍ.\nوالغِشْيَانُ: إتْيَانُ الرَّجُلِ المَرْأةَ.\nوغُشِيَ عليه: ذَهَبَ عَقْلُه.\nوالغَشْوَاءُ من الشّاءِ: التي يَغْشى وَجْهَها كُلَّه بَيَاضٌ.\nويقولون: غَشَاني (¬٢) اللَّيْلُ: أي غَشِيَني. (و. ا. ي)\nغشو:\nالغَشَاوَةُ والغِشَاوَةُ: ما غَشّى القَلْبَ.\nوغاشِيَةُ الرَّحْلِ (¬١) والسَّيْفِ: غِطاؤه. والحَدِيدةُ التي فَوْقَ المُؤخّرَةِ.\nوالذين يَغْشَوْنَكَ ويَرْجُونَ فَضْلَكَ: غاشِيَةٌ. وهي القِيامَةُ أيضاً. وداءٌ في الجَوْفِ، رَمَاهُ اللَّهُ بغاشِيَةٍ.\nوالغِشْيَانُ: إتْيَانُ الرَّجُلِ المَرْأةَ.\nوغُشِيَ عليه: ذَهَبَ عَقْلُه.\nوالغَشْوَاءُ من الشّاءِ: التي يَغْشى وَجْهَها كُلَّه بَيَاضٌ.\nويقولون: غَشَاني (¬٢) اللَّيْلُ: أي غَشِيَني.\nوشغ:",
    "pg": "5:101"
  },
  "غصب": {
    "def": "الغَصْبُ: أخْذُ الشَّيْءِ ظُلْماً وقَهْراً، غَصَبَ يَغْصِبُ غَصْباً، واغْتَصَبَ اغْتِصاباً. [/١٤٣ ب]\nغصب:\nالغَصْبُ: أخْذُ الشَّيْءِ ظُلْماً وقَهْراً، غَصَبَ يَغْصِبُ غَصْباً، واغْتَصَبَ اغْتِصاباً.\nصبغ:",
    "pg": "5:9"
  },
  "غصن": {
    "def": "الغُصْنُ: غُصْنُ الشَّجَرِ (¬١٧)، والجميع الغُصُون والأغْصَان، وتَصْغِيرُها غُصَيْنَةٌ. وغَصَنْتُ غُصْنَ الشَّجَرَةِ أغْصِنُه: إذا مَدَدْتَه. نغص (¬١٨):\nنَغِصَ (¬١٩) الرَّجُلُ نَغَصاً: إذا لم تَتِمَّ له هَنَاءتُه (¬٢٠)، ويُشَدَّد أيضاً.\nوالنَّغَصُ: في المَشْرَب أيضاً.\nغنص:",
    "pg": "5:7-8"
  },
  "غضض": {
    "def": "الغَضُّ الغَضِيْضُ: الطَّري، بَيِّنُ الغَضَاضَةِ والغُضُوضَةِ. وامْرَأةٌ غاضَّةٌ: طَرِيَّةٌ غَضَّةٌ.\nوالغَضَاضَةُ: فُتُورٌ في الطَّرْفِ، غَضَّ وأغْضى: إذا دانى بَيْنَ جَفْنَيْه ولم يُلاقِ.\nوالغَضُّ: وَزْعُ العَذْل.\nوالغَضْغَضَةُ: الغَيْضُ (¬١).\nوما غَضَضْتُكَ شَيْئاً: أي ما نَقَصْتُك، وأنا أغُضُّه، والاسْمُ الغُضَّة.\nورَجُلٌ غَضِيْضٌ من قَوْمٍ أغِضَّةٍ وأغِضّاء: وهم الأذِلَّةُ.\nوغَضَضْتُ الغُصْنَ: إذا كَسَرْتَه [/١٣٩ ب] فلم تُنْعِمْ كَسْرَه.\nوغَضَضْتُ عنه: كَفَفْت عنه.\nوالغَضِيْضُ: الطَّلْعُ. غض:\nالغَضُّ الغَضِيْضُ: الطَّري، بَيِّنُ الغَضَاضَةِ والغُضُوضَةِ. وامْرَأةٌ غاضَّةٌ: طَرِيَّةٌ غَضَّةٌ.\nوالغَضَاضَةُ: فُتُورٌ في الطَّرْفِ، غَضَّ وأغْضى: إذا دانى بَيْنَ جَفْنَيْه ولم يُلاقِ.\nوالغَضُّ: وَزْعُ العَذْل.\nوالغَضْغَضَةُ: الغَيْضُ (¬١).\nوما غَضَضْتُكَ شَيْئاً: أي ما نَقَصْتُك، وأنا أغُضُّه، والاسْمُ الغُضَّة.\nورَجُلٌ غَضِيْضٌ من قَوْمٍ أغِضَّةٍ وأغِضّاء: وهم الأذِلَّةُ.\nوغَضَضْتُ الغُصْنَ: إذا كَسَرْتَه [/١٣٩ ب] فلم تُنْعِمْ كَسْرَه.\nوغَضَضْتُ عنه: كَفَفْت عنه.\nوالغَضِيْضُ: الطَّلْعُ.\nضغ:",
    "pg": "4:496"
  },
  "غضغض": {
    "def": "الغَضُّ الغَضِيْضُ: الطَّري، بَيِّنُ الغَضَاضَةِ والغُضُوضَةِ. وامْرَأةٌ غاضَّةٌ: طَرِيَّةٌ غَضَّةٌ.\nوالغَضَاضَةُ: فُتُورٌ في الطَّرْفِ، غَضَّ وأغْضى: إذا دانى بَيْنَ جَفْنَيْه ولم يُلاقِ.\nوالغَضُّ: وَزْعُ العَذْل.\nوالغَضْغَضَةُ: الغَيْضُ (¬١).\nوما غَضَضْتُكَ شَيْئاً: أي ما نَقَصْتُك، وأنا أغُضُّه، والاسْمُ الغُضَّة.\nورَجُلٌ غَضِيْضٌ من قَوْمٍ أغِضَّةٍ وأغِضّاء: وهم الأذِلَّةُ.\nوغَضَضْتُ الغُصْنَ: إذا كَسَرْتَه [/١٣٩ ب] فلم تُنْعِمْ كَسْرَه.\nوغَضَضْتُ عنه: كَفَفْت عنه.\nوالغَضِيْضُ: الطَّلْعُ. غض:\nالغَضُّ الغَضِيْضُ: الطَّري، بَيِّنُ الغَضَاضَةِ والغُضُوضَةِ. وامْرَأةٌ غاضَّةٌ: طَرِيَّةٌ غَضَّةٌ.\nوالغَضَاضَةُ: فُتُورٌ في الطَّرْفِ، غَضَّ وأغْضى: إذا دانى بَيْنَ جَفْنَيْه ولم يُلاقِ.\nوالغَضُّ: وَزْعُ العَذْل.\nوالغَضْغَضَةُ: الغَيْضُ (¬١).\nوما غَضَضْتُكَ شَيْئاً: أي ما نَقَصْتُك، وأنا أغُضُّه، والاسْمُ الغُضَّة.\nورَجُلٌ غَضِيْضٌ من قَوْمٍ أغِضَّةٍ وأغِضّاء: وهم الأذِلَّةُ.\nوغَضَضْتُ الغُصْنَ: إذا كَسَرْتَه [/١٣٩ ب] فلم تُنْعِمْ كَسْرَه.\nوغَضَضْتُ عنه: كَفَفْت عنه.\nوالغَضِيْضُ: الطَّلْعُ.\nضغ:",
    "pg": "4:496"
  },
  "غضى": {
    "def": "الإِغْضَاءُ: إدْناءُ الجُفُونِ. وأغْضَيْتُ على القَذى. وغَضَوْتُ عليه: أي سَكَتُّ.\nولَيْلٌ غاضٍ [يَغْضُو غُضُوّاً: إذا] (¬٢) غَشِيَ كُلَّ شَيْءٍ.\nونارٌ غاضِيَةٌ: عَظِيمةٌ. وغَضَوِيَّةٌ: من الغَضى (¬٣) والغَضَاة، و [الجَميعُ] (¬٤) الغَضى (¬٥). والغَضْيَاءُ: مُجْتَمَعُ مَنْبِتِها. وأرْضٌ غَضْيَاءُ وغَضِيَةٌ: كثيرة الغَضى.\nوإبلٌ غَضَايا، وغَضِيَتْ (¬٦): اشْتَكَتْ من أكْلِه، وغاضٍ: يُرْعى الغَضى.\nوشَيْءٌ غاضٍ أحْسَن الغُضُوِّ (¬٧): أي جامٌّ وافِرٌ.\nوأتانا بغَضْياءَ (¬٨): أي بمائةٍ من الإِبل، وهي مَعْرِفةٌ. وهي-أيضاً-: الأرضُ الغَلِيظةُ. واسْمُ ابنِ غَضْياءَ منه.\nضغو (¬٩):\nالضُّغَاءُ: صَوْتُ الذَّلِيلِ، [و] (¬١٠) أضْغَيْتُه فَضَغا ضَغْواً: أي اسْتَخْذى. (و. ا. ي)\nغوص:",
    "pg": "5:103-105"
  },
  "غطف": {
    "def": "غُطَيْفٌ: في مُرَادٍ.\nوغَطَفانُ: من قَيْسٍ.\nوعَيْشٌ أغْطَفُ: أي ناعِمٌ.\nوالغَطَفُ: طُولُ الأشْفارِ وانْعِطافُه؛ كالوَطَف (¬١٤). طغن:\nالخارزنجيُّ: الطُّوْغانُ: البازي الكبيرُ، وجَمْعُه طَواغِيْنُ.\n\n\nغطف:\nغُطَيْفٌ: في مُرَادٍ.\nوغَطَفانُ: من قَيْسٍ.\nوعَيْشٌ أغْطَفُ: أي ناعِمٌ.\nوالغَطَفُ: طُولُ الأشْفارِ وانْعِطافُه؛ كالوَطَف (¬١٤).\n\n\nغبط:",
    "pg": "5:32"
  },
  "غطل": {
    "def": "الغَيْطَلُ والغَيْطَلَةُ: شَجَرٌ مُلْتَفٌّ أو عُشْبٌ. والنُّعَاسُ الغالبُ. واسْمُ البَقَرَةِ.\nوجَلَبُ (¬٩) القَوْمِ وأصواتُهم. وجَماعَةُ الوَحْشِ. والْتِباسُ الظَّلامِ (¬١٠) وتَراكُمُه، وكذلك الغَيْطُول.\nوالمُغْطَئلُّ (¬١١): الراكِبُ بعضُه بعضاً. وهو من الشَّجَرِ: المُلْتَفُّ.\nوغَيْطَلُ الضُّحى: حَيثُ تكونُ الشمسُ من مَشْرِقها كهيئتها من مغربها وقتَ الظُّهْر.\nوغَيَاطِلُ الدُّنيا: نَعِيْمُها.\nوغَطَلَتِ السَّماءُ يومَنا هذا وأغْطَلَتْ (¬١٢): أي غَطَّتْ ضَوءَ الشَّمس. غطل:\nالغَيْطَلُ والغَيْطَلَةُ: شَجَرٌ مُلْتَفٌّ أو عُشْبٌ. والنُّعَاسُ الغالبُ. واسْمُ البَقَرَةِ.\nوجَلَبُ (¬٩) القَوْمِ وأصواتُهم. وجَماعَةُ الوَحْشِ. والْتِباسُ الظَّلامِ (¬١٠) وتَراكُمُه، وكذلك الغَيْطُول.\nوالمُغْطَئلُّ (¬١١): الراكِبُ بعضُه بعضاً. وهو من الشَّجَرِ: المُلْتَفُّ.\nوغَيْطَلُ الضُّحى: حَيثُ تكونُ الشمسُ من مَشْرِقها كهيئتها من مغربها وقتَ الظُّهْر.\nوغَيَاطِلُ الدُّنيا: نَعِيْمُها.\nوغَطَلَتِ السَّماءُ يومَنا هذا وأغْطَلَتْ (¬١٢): أي غَطَّتْ ضَوءَ الشَّمس.\nلغط:",
    "pg": "5:31"
  },
  "غطم": {
    "def": "الغَطْمَطَةُ: الْتِطامُ الأمواج. وبَحْرٌ غِطَمٌّ غِطْيَمٌّ (¬٣١): شَديدُ الالْتِطام. وعَدَدٌ غِطْيَمٌّ (¬٣٢): كثيرٌ، وكذلك الغُطامِطُ.\nوالغَيْطَمُّ والغُطَامِطُ: العُجَالِطُ من الألبانِ الرّائبُ.\nطغم:",
    "pg": "5:33-34"
  },
  "غطو": {
    "def": "غَطا اللَّيْلُ يَغْطُو: إذا غَشِيَ (¬١٣). ولَيْلٌ غاطٍ ومُغْطٍ. وغَطا عليهم البَلاءُ ونحوُه.\nوغَطا به الشَّبابُ: ارْتَفَعَ به، وكذلك كلُّ شَيْءٍ طالَ على شَيْءٍ. غطى:\nالغِطَاءُ: ما غَطَّيْتَ به، والجميع الأغْطِيَةُ.\nوإذا امْتَلأَ الشابُّ شَباباً (¬٨) قيل: غَطى يَغْطي (¬٩) غَطْياً وغُطِيّاً.\nوالغَطْيُ: ارتفاعُ (¬١٠) الكَرْمِ على الدِّعَمِ.\nوغَطى اللَّيْلُ يَغْطي غَطَيَاناً (¬١١): أظْلَمَ، فهو غاطٍ. وخُذْ هذا قَبْلَ أنْ يُغْطِيَ عليك اللَّيْلُ (¬١٢)؛ من أغْطَيْتُ.\nغطو:\nغَطا اللَّيْلُ يَغْطُو: إذا غَشِيَ (¬١٣). ولَيْلٌ غاطٍ ومُغْطٍ. وغَطا عليهم البَلاءُ ونحوُه.\nوغَطا به الشَّبابُ: ارْتَفَعَ به، وكذلك كلُّ شَيْءٍ طالَ على شَيْءٍ.\nطغو:",
    "pg": "5:112"
  },
  "غطى": {
    "def": "الغِطَاءُ: ما غَطَّيْتَ به، والجميع الأغْطِيَةُ.\nوإذا امْتَلأَ الشابُّ شَباباً (¬٨) قيل: غَطى يَغْطي (¬٩) غَطْياً وغُطِيّاً.\nوالغَطْيُ: ارتفاعُ (¬١٠) الكَرْمِ على الدِّعَمِ.\nوغَطى اللَّيْلُ يَغْطي غَطَيَاناً (¬١١): أظْلَمَ، فهو غاطٍ. وخُذْ هذا قَبْلَ أنْ يُغْطِيَ عليك اللَّيْلُ (¬١٢)؛ من أغْطَيْتُ. غطى:\nالغِطَاءُ: ما غَطَّيْتَ به، والجميع الأغْطِيَةُ.\nوإذا امْتَلأَ الشابُّ شَباباً (¬٨) قيل: غَطى يَغْطي (¬٩) غَطْياً وغُطِيّاً.\nوالغَطْيُ: ارتفاعُ (¬١٠) الكَرْمِ على الدِّعَمِ.\nوغَطى اللَّيْلُ يَغْطي غَطَيَاناً (¬١١): أظْلَمَ، فهو غاطٍ. وخُذْ هذا قَبْلَ أنْ يُغْطِيَ عليك اللَّيْلُ (¬١٢)؛ من أغْطَيْتُ.\nغطو:",
    "pg": "5:112"
  },
  "غفر": {
    "def": "الغُفْرانُ والمَغْفِرَةُ والغَفِيرةُ والغَفْرُ: واحِدٌ.\nوالغَفِيرةُ والغَفِيرُ: الشَّيْءُ الهَيِّنُ الذي تَغْتَفِرُه أي تَحْتَقِرُه.\nواغْتَفَرْتُ ذاكَ: [أي] (¬٣٧) احْتَمَلْتَه.\nوغَفَرَ الجُرْحُ يَغْفِرُ غَفْراً.\nوغَفَرَ الثَّوْبَ: إذا أثارَ زِئْبرَه.\nوغَفِرَتِ الجارِيَةُ غَفَراً: إذا كانَ وَجْهُها نَقِيّاً ثُمَّ نَبَتَ فيه الشَّعرُ.\nوالغَفِيْرُ والغِفَارَةُ: شَعرٌ في العُنُقِ واللّحْيَيْنِ.\nوشَعرُ ساقِ المَرْأةِ: الغَفَرُ.\nوالغَفَائرُ: الذَّوائبُ.\nوالغُفَارُ (¬٣٨): الشَّعرُ الرَّقيقُ الذي يكونُ على الجَبْهَةِ والساقِ.\nوالغَفَرُ: شَعرُ الأُذُنِ.\nوالمِغْفَرُ: وقايَةٌ للرَّأْسِ، وكذلك الغَفّارَةُ (¬٣٩).\nومِغْفَرُ البَيْضَةِ: رَفْرَفُها من حِلَقِ الحَدِيد.\nوالغِفَارَةُ: خِرْقَةٌ يَضَعُها المُدَّهِنُ على هامَتِه، وكذلك الخِرْقَةُ التي تُلَفُّ على سِيَةِ (¬٤٠) القَوْسِ لِتُلَفَّ فَوْقَها إطْنابَةُ الوَتَرِ.\nواصْبُغْ ثَوْبَكَ فإِنَّه أغْفَرُ للوَسَخِ: أي أغْطا وأسْتَرُ. وجاءَ القَوْمُ جَمّاءَ الغَفِيرِ: أي بجَماعَتِهم. ومَرَرْتُ بهم الجَمَّاءَ الغَفِيرَ وجَمّاءَ الغَفِيرى وجَمّاءَ الغَفِيرةِ.\nوالغَفِيْرُ: ذو المِغْفَرِ.\nوالغُفْرُ: وَلَدُ الأرْوى. والمِغْفَرُ (¬٤١): الأُرْوِيَّةُ، وكذلك أُمُّ غُفْرٍ، وهي المُغْفِرَةُ (¬٤٢).\nوالغَفْرُ: مَنْزِلٌ من مَنازِل القَمَر. والوِعاءُ يُوْعى فيه الشَّيْءُ. والكِنانَةُ.\nوالثِّيابُ. والمَتَاعُ يُجْعَلُ في الغِرَارَة.\nوجَبَلٌ يُسَمّى غِفَارَةَ.\nوالمِغْفَارُ: دُوَدِمٌ (¬٤٣) يَخْرُجُ من العُرْفُطِ ومن الإِجّاص أيضاً، وكذلك المُغْفُورُ والمِغْفَرَةُ (¬٤٤)، خَرَجْنا (¬٤٥) نَتَمَغْفَرُ ونَتَغَفَّرُ.\nوفي المَثَل (¬٤٦): «فَسَدَ هذا الجَنى إلاّ أنْ تَكُدَّ المِغْفَرا».\nوغُفِرَ الرَّجُلُ: إذا بَرَأ من مَرَضِه، وكذلك إذا نُكِسَ فيه، وهو من الأضداد، ومَصْدَرُه: غَفْرٌ وغُفُورٌ. وغَفَرَ الجُرْحُ: فَسَدَ.\nوالغَفَرُ: كَلَأٌ صَغيرٌ. وأغْفَرَتِ الأرضُ: نَبَتَ فيها ذاكَ.\nوغَفَرَ الفَخُّ بالصَّيْدِ: وَقَعَ عليه.\nواغْفِرُوا هذا الأمْرَ بغُفْرَتِه: أي أصْلِحُوه بما ينبغي أنْ يُصْلَحَ به. رفغ:",
    "pg": "5:68-70"
  },
  "غفص": {
    "def": "غافَصْتُ فلاناً مُغَافَصَةً: إذا أخَذْتَه على غِرَّةٍ فَرَكِبْتَه بِمَساءةٍ (¬٢٤).\nوالغافِصَةُ: من أوَازِمِ (¬٢٥) الدَّهر.\nصفغ (¬٢٦):\nمُهْمَلٌ [عنده] (¬٢٧).\n[الخارزَنْجيُّ] (¬٢٨): الصَّفْغُ: القَمْحُ، صَفَغْتُ الدَّواءَ صَفْغاً. [/١٤٣ ب]\nغصب:",
    "pg": "5:8-9"
  },
  "غفل": {
    "def": "غَفَلَ يَغْفُلُ غَفْلَةً وغُفُولاً. والتَّغافُلُ: التَّعَمُّدُ. وأغْفَلْتُ (¬١٠) الشَّيْءَ: تَرَكْتَه غُفْلاً (¬١١) وأنْتَ له ذاكِرٌ. والمُغَفَّل: مَنْ لا فِطْنَةَ له.\nوالغُفْلُ: المُقَيَّدُ لا يُرْجى خَيْرُه ولا يُخْشى شَرُّه.\nوالغُفْلُ: سَبْسَبٌ مُتَيِّهٌ لا علامَة فيه.\nودابَّةٌ غُفْلٌ: ليس عليها سِمَةٌ.\nوقِدْحٌ غُفْلٌ: لا نَصِيْبَ له ولا غُرْمَ عليه. وأرْضٌ غُفْلٌ: لم تُمْطَرْ.\nوالمَغْفَلَةُ: هي العَنْفَقَةُ، وسُمِّيَتْ بذلك لأنَّ كثيراً من الناسِ يَغْفُلُ عنها عند الوضوء.\nلغف:",
    "pg": "5:84-85"
  },
  "غفو": {
    "def": "أغْفى الرَّجُلُ: دَخَلَ في النَّوْم، وغَفَا يَغْفُو.\nويُقال للزُّبْيَةِ: غُفْوَةٌ وغُفْيَةٌ وغِفْيَةٌ.\nوغَفا على الماءِ يَغْفُو: بمعنى طَفا.\nوالغَفَا: ما يُخْرَجُ من الطَّعام فَيُرْمى به، وكذلك من البُسْرِ، وأغْفى الطَّعامُ:\nكَثُرَ غَفَاه وغَفَاتُه.\nوالغَفَا: غُثَاءُ السَّيْلِ (¬٦).\nوانْغَفى الشَّيْءُ: انْكَسَرَ.\nوالغُفَاءَةُ (¬٧): البَيَاضُ على الحَدَقَة. وهو في عَيْشٍ أغْيَفَ: أي ناعِمٍ.\nوالغافُ: يَنْبُوتٌ (¬٥) عِظامٌ كالشَّجَر.\nوالغَيْفُ: جَماعَةٌ من الطَّير.\nوالغَيّافُ: الذي طالتْ لِحْيَتُه وعرضَتْ من كلِّ جانبٍ، وقَوْمٌ غَيّافُوْنَ.\nغفو:\nأغْفى الرَّجُلُ: دَخَلَ في النَّوْم، وغَفَا يَغْفُو.\nويُقال للزُّبْيَةِ: غُفْوَةٌ وغُفْيَةٌ وغِفْيَةٌ.\nوغَفا على الماءِ يَغْفُو: بمعنى طَفا.\nوالغَفَا: ما يُخْرَجُ من الطَّعام فَيُرْمى به، وكذلك من البُسْرِ، وأغْفى الطَّعامُ:\nكَثُرَ غَفَاه وغَفَاتُه.\nوالغَفَا: غُثَاءُ السَّيْلِ (¬٦).\nوانْغَفى الشَّيْءُ: انْكَسَرَ.\nوالغُفَاءَةُ (¬٧): البَيَاضُ على الحَدَقَة.\nفغى:",
    "pg": "5:138"
  },
  "غلب": {
    "def": "غَلَبَ يَغْلِبُ غَلَبَةً وغَلَباً. والغِلابُ: النِّزَاعُ. واللَّهُ الغَلاّبُ.\nوأسَدٌ (¬١٩) أغْلَبُ، والفِعْلُ غَلِبَ يَغْلَبُ غَلَباً.\nوالغَلَبُ: داءٌ.\nوهَضْبَةٌ غَلْبَاءُ. وعِزَّةٌ غَلْبَاءُ. وكانتْ تُسَمّى تَغْلِبُ: الغَلْباءَ.\nوالغُلُبّى: الغالِبُ. ورَجُلٌ غُلُبَّةٌ: يَغْلِبُ سَرِيعاً. والغَلابِيَةُ: الغَلَبَةُ.\n[والغُلْبَةُ: المُغالَبَةُ] (¬٢٠).\nواغْلَوْلَبَ العُشْبُ في الأرضِ: إذا بَلَغَ كُلَّ مَبْلَغٍ.\nوالنسبةُ إلى تَغْلِبَ: بالكَسْر والفَتْح.\nوبَعِيْرٌ غُلالِبٌ: الذي (¬٢١) يَغْلِبُ بسَيْرِه.\nوقيل في قَوْلِ الراجِزِ:\nيا لَيْتَ دَيْنَ غِلْبَتي … قد حَلاّ\nأتى وَقْتي (¬٢٢) الذي أغْلِبُ فيه الناسَ.\nوغَلابِ: اسْمُ امْرَأَةٍ. غلب:\nغَلَبَ يَغْلِبُ غَلَبَةً وغَلَباً. والغِلابُ: النِّزَاعُ. واللَّهُ الغَلاّبُ.\nوأسَدٌ (¬١٩) أغْلَبُ، والفِعْلُ غَلِبَ يَغْلَبُ غَلَباً.\nوالغَلَبُ: داءٌ.\nوهَضْبَةٌ غَلْبَاءُ. وعِزَّةٌ غَلْبَاءُ. وكانتْ تُسَمّى تَغْلِبُ: الغَلْباءَ.\nوالغُلُبّى: الغالِبُ. ورَجُلٌ غُلُبَّةٌ: يَغْلِبُ سَرِيعاً. والغَلابِيَةُ: الغَلَبَةُ.\n[والغُلْبَةُ: المُغالَبَةُ] (¬٢٠).\nواغْلَوْلَبَ العُشْبُ في الأرضِ: إذا بَلَغَ كُلَّ مَبْلَغٍ.\nوالنسبةُ إلى تَغْلِبَ: بالكَسْر والفَتْح.\nوبَعِيْرٌ غُلالِبٌ: الذي (¬٢١) يَغْلِبُ بسَيْرِه.\nوقيل في قَوْلِ الراجِزِ:\nيا لَيْتَ دَيْنَ غِلْبَتي … قد حَلاّ\nأتى وَقْتي (¬٢٢) الذي أغْلِبُ فيه الناسَ.\nوغَلابِ: اسْمُ امْرَأَةٍ.\nلغب:",
    "pg": "5:86"
  },
  "غلت": {
    "def": "الغَلَتُ في الحِسَاب: كالغَلَط في الكَلام. و (¬٧) رَجُلٌ غَلِتٌ. واغْتَلَتَني فلانٌ وتَغَلَّتَني: [أي] (¬٨) أخَذَني (¬٩) على غِرَّةٍ.\nوالغَلُوْتُ: الذي يَغْلَتُ كثيراً.\n\n\nنتغ:",
    "pg": "5:47-48"
  },
  "غلث": {
    "def": "الغَلْثُ: الخَلْطُ، طَعامٌ مَغْلُوثٌ: [أي] (¬٣٠) مَخْلُوطٌ.\nوغَلَثَ (¬٣١) الطائرُ: إذا هاعَ.\nوالغَلِثُ: الذي تأخُذُه عن الطَّعام والشَّرَابِ نَشْوَةٌ وتَمَايُلٌ. ومن النُّعَاسِ:\nتَكْسِيرُهُ وكَسَلُه.\nوالمُغَلِّثُ من الوَجَعِ: [هو] (¬٣٢) المُقَارِبُ (¬٣٣).\nوالمُغالِثُ: المُلازِمُ للشَّيْءِ. والغَلْثى: شَجَرَةٌ من شَجَرِ الجِبالِ يُغَلَّثُ بها للسِّباع والطَّيْرِ (¬٣٤).\nوالغَلِثُ والغَلَثِيُّ: الدّاهِيَةُ.\nوشَعرٌ غَلِيثٌ: أشْمَطُ.\nوالغَلَثُ في الغَضَب: الاخْتِلاطُ.\nوسِقَاءٌ مَغْلُوثٌ: مَدْبُوغٌ بالتَّمر أو البُسْرِ (¬٣٥).\n\n\nغنث:",
    "pg": "5:58-59"
  },
  "غلس": {
    "def": "الغَلَسُ: ظَلامُ آخِرِ اللَّيْل. وغَلَّسْنا: سِرْنا (¬٢١) بغَلَسٍ.\nويُقال (¬٢٢): سَقَطَ في تُغَلِّسَ (¬٢٣): وهي الدّاهِيَةُ، كأنَّهم (¬٢٤) أرادوا:\nيَتَغَلَّسُ داهِيَةً مُباكرةً، كما قال:\nإنَّ الحَوادِثَ قد يَطْرُقْنَ أسحارا\nوالأصل في هذا أن الغارات كانتْ تَكْثُرُ في آخِرِ اللَّيْل (¬٢٥).\nوغُلَيْسٌ (¬٢٦): من ألْقابِ الحِمار؛ لأنَّه أغْلَسُ اللَّوْن. لغس:",
    "pg": "5:15-16"
  },
  "غلص": {
    "def": "الغَلْصُ: قَطْعُ الغَلْصَمَةِ. وأرْضٌ مُصْغِرَةٌ: إذا كان نَبْتُها صَغِيراً لم يَطُلْ.\nوارْتَبَعَ القَومُ لِيُصْغِروا: أي يُوَلِّدوا الأصاغِرَ، والمَصْدَرُ الإِصْغَار.\nرصغ:\nالرُّصْغُ: لُغَةٌ في الرُّسْغ.\n\n\nصغل:\nالصَّغِلُ: لُغَةٌ في السَّغِلِ (¬١٥) وهو السَّيِّئُ الغِذَاء.\nلصغ:\nلَصَغَ الجِلْدُ لُصُوْغاً: إذا يَبِسَ على العَظْم عَجفاً.\nصلغ (¬١٦):\nصَلَغَتِ الشّاةُ صُلُوغاً: إذا تَمَّتْ أسنانُها، والصّالِغُ في الشّاءِ: كالقارِحِ في الخَيْل.\nوالصَّلْغَةُ: السَّفِينةُ الكَبِيرة.\nغلص:\nالغَلْصُ: قَطْعُ الغَلْصَمَةِ.\n\n\nغصن:",
    "pg": "5:7"
  },
  "غلط": {
    "def": "الغَلَطُ: في كلِّ شَيْءٍ يَعْيَا به الإِنسانُ، غَلِطَ يَغْلَطُ غَلَطاً وأُغْلُوطةً.\n\n\n[مُهْمَلات] (¬١٣): طغن:",
    "pg": "5:31-32"
  },
  "غلظ": {
    "def": "الغِلَظُ: مَصْدَرُ الغَليظِ في الخِلْقَة. واسْتَغْلَظَ والنَّباتُ والشَّجَرُ. وأغْلَظْتُ هذا الثَّوبَ: وَجَدْتُه غَلِيظاً، واسْتَغْلَظْتُه.\nوالتَّغْلِيظُ: الشِّدَّةُ في اليَمِين. هو ذو غُلْظَةٍ وغِلاظَةٍ وغِلْظَةٍ. وغَلَّظْتُ عليه وأغْلَظْتُ.\nوالغَلْظُ من الأرضِ: الخَشِنُ، والمُغْلِظُ: الذي نَزَلَ فيه. غلظ:\nالغِلَظُ: مَصْدَرُ الغَليظِ في الخِلْقَة. واسْتَغْلَظَ والنَّباتُ والشَّجَرُ. وأغْلَظْتُ هذا الثَّوبَ: وَجَدْتُه غَلِيظاً، واسْتَغْلَظْتُه.\nوالتَّغْلِيظُ: الشِّدَّةُ في اليَمِين. هو ذو غُلْظَةٍ وغِلاظَةٍ وغِلْظَةٍ. وغَلَّظْتُ عليه وأغْلَظْتُ.\nوالغَلْظُ من الأرضِ: الخَشِنُ، والمُغْلِظُ: الذي نَزَلَ فيه.\n\n\nغنظ:",
    "pg": "5:51"
  },
  "غلف": {
    "def": "الأغْلَفُ: الأقْلَفُ. والغُلْفَةُ: القُلْفَةُ (¬٧).\nوقَلْبٌ أغْلَفُ: كأنَّما غُشِّيَ غِلافاً، وقُلُوبٌ غُلْفٌ.\nوالغِلافُ: الصِّوَانُ، غَلَّفْتُ القارُوْرَةَ وأغْلَفْتُها.\nوعَيْشٌ أغْلَفُ: أي (¬٨) ناعِمٌ.\nوعامٌ أغْلَفُ (¬٩): كَثِيرُ النَّباتِ.\nوتَغَلَّفَ بالغالِيَةِ وتَغَلَّلَ: واحِدٌ.\nوسَيْفٌ أغْلَفُ وقَوْسٌ غَلْفَاءُ: في غِلافٍ. ويقولون لَغَنَّه (¬٦): في معنى لَعَلَّه.\nوالْغَانَّ النَّباتُ: إذا الْتَفَّ وطالَ.\n\n\nغلف:\nالأغْلَفُ: الأقْلَفُ. والغُلْفَةُ: القُلْفَةُ (¬٧).\nوقَلْبٌ أغْلَفُ: كأنَّما غُشِّيَ غِلافاً، وقُلُوبٌ غُلْفٌ.\nوالغِلافُ: الصِّوَانُ، غَلَّفْتُ القارُوْرَةَ وأغْلَفْتُها.\nوعَيْشٌ أغْلَفُ: أي (¬٨) ناعِمٌ.\nوعامٌ أغْلَفُ (¬٩): كَثِيرُ النَّباتِ.\nوتَغَلَّفَ بالغالِيَةِ وتَغَلَّلَ: واحِدٌ.\nوسَيْفٌ أغْلَفُ وقَوْسٌ غَلْفَاءُ: في غِلافٍ.\nغفل:",
    "pg": "5:84"
  },
  "غلم": {
    "def": "غَلِمَ (¬٣٦) يَغْلَمُ غُلْمَةً وغَلَماً، واغْتَلَمَ. والمُغْتَلِمُ والغِلِّيْمُ سَوَاءٌ، ويُقال مِغْلِيْمٌ (¬٣٧). وامْرَأةٌ غِلِّيْمٌ (¬٣٨): [أي] (¬٣٩) مُغْتَلِمَةٌ. وغُلامٌ بَيِّنُ الغِلْمَةِ (¬٤٠) [/١٤٩ ب] والغُلُومَةِ والغُلامِيَّةِ.\nوالغُلامُ: الطّارُّ الشّارِبِ. ويُقال للغُلام: غُلَمٌ.\nوالغَيْلَمُ (¬٤١): مَوْضِعٌ. والسُّلَحْفَاةُ (¬٤٢) الذَّكَرُ. والمِدْرى. ومَنْبَعُ الماءِ في الآبار. والشّابُّ (¬٤٣) العَرِيضُ المَفْرِقِ الكَثيرُ الشَّعرِ، وهو الغَيْلَميُّ (¬٤٤) أيضاً.\nوما بالدارِ غَيْلَمٌ: أي أحَدٌ.\nلغم:",
    "pg": "5:88-89"
  },
  "غلن": {
    "def": "مُهْمَلٌ عنده (¬٣).\nالخارزنجيُّ: الغَلَنُ: زِيادَةُ الشَّبابِ، قد غَلَنَ الشَّبابُ-مِثْلُ غَلا-: أي ازْدادَ. وهو في غُلَوَانِهِ (¬٤) وغُلَوائه: أي شِدَّتِه وكثرتِه. (¬١)\nنغل:\nالنَّغِلُ: الأدِيمُ الفاسِدُ في دِبَاغِه، نَغِلَ يَنْغَلُ نَغَلاً. وجَوْزَةٌ نَغِلَةٌ.\nوالنَّغْلُ: وَلَدُ زِنْيَةٍ، والجارِيَةُ نَغْلَةٌ. ونَغِيْلٌ مِثْلُه (¬٢).\nغلن:\nمُهْمَلٌ عنده (¬٣).\nالخارزنجيُّ: الغَلَنُ: زِيادَةُ الشَّبابِ، قد غَلَنَ الشَّبابُ-مِثْلُ غَلا-: أي ازْدادَ. وهو في غُلَوَانِهِ (¬٤) وغُلَوائه: أي شِدَّتِه وكثرتِه.\nلغن:",
    "pg": "5:83"
  },
  "غلو": {
    "def": "غلا السِّعْرُ يَغْلُو غَلاءً-مَمْدُودٌ-. ويُغالي (¬١) اللَّحْم وباللَّحْم.\nوغَلا في الأمْرِ غُلُوّاً: إذا جاوَزَ حَدَّه.\nوفي الشِّرى: أغْلَيْتُ به وغالَيْتُ.\nويَغْلُو بالسَّهْم غَلْواً.\nوفي المَثَل (¬٢): «جَرْيُ المُذَكِّيَات غِلاءٌ (¬٣)». والمُغالي به: الرافِعُ يَدَهُ إلى أقْصى الغايَةِ. وكُلُّ مرْمَاةٍ غَلْوَةٌ. والمِغْلاةُ: سَهْمٌ يُتَّخَذُ لِمُغالاةِ الغَلْوَةِ، وهو (¬٤) المِغْلى أيضاً.\nوالدّابَّةُ تَغْلُو في سَيْرِها غُلُوّاً.\nوتَغالى النَّبْتُ: طالَ وارْتَفَعَ.\nوتغالى لَحْمُ الدابَّةِ: تَحَسَّرَ عِنْدَ الضُّمْرِ (¬٥). وفَعَلَ ذلك (¬٦) في غَلْوَةِ شَبابِه: أي في عُنْفُوانِه، وغُلَوائه (¬٧).\nوالغَلاءُ -مَمْدُودٌ-: سَمَكَةٌ نَحْوٌ من شِبْرٍ، وجَمْعُه أغْلِيَةٌ.\n[غلي]\nوغَلَتِ القِدْرُ تَغْلي غَلَياناً وغَلْياً.\nوالغالِيَةُ: مَعْروفةٌ.\nغول:",
    "pg": "5:129-130"
  },
  "غمت": {
    "def": "مُهْمَلٌ عنده (¬٢٢).\nالخارزنجيُّ: غَمَتَ نَفساً: إذا قالَ برأْسِه في الماء عند الشُّرْب (¬٢٣).\nوغُمِتَ (¬٢٤) من الوَدَك: إذا أسْنَقَه (¬٢٥). وغَمَتَه الطَّعامُ يَغْمُتُه (¬٢٦): إذا أتْخَمَه. غلظ:",
    "pg": "5:50-51"
  },
  "غمد": {
    "def": "الغِمْدُ: غِلافُ السَّيْفِ، أغْمَدْتُ السَّيْفَ وغَمَدْتُ. والغُمُدّانُ: غِمْدُ السَّيف.\nوتَغَمَّدْتُ فلاناً: إذا أخَذْتَه تَحْتَكَ (¬٧٥) حتى تُغَطِّيَه.\nوغامِدٌ: حيٌّ من اليَمَن.\nوتَرَكْتُ المالَ وغيرَه غامِداً: أي جامّاً وافراً.\nورَكيٌّ غامِدٌ: وارى التُّرَابُ ماءه فهو دِفَانٌ (¬٧٦).\nوالتَّغَمُّدُ: المَلْءُ. غمد:\nالغِمْدُ: غِلافُ السَّيْفِ، أغْمَدْتُ السَّيْفَ وغَمَدْتُ. والغُمُدّانُ: غِمْدُ السَّيف.\nوتَغَمَّدْتُ فلاناً: إذا أخَذْتَه تَحْتَكَ (¬٧٥) حتى تُغَطِّيَه.\nوغامِدٌ: حيٌّ من اليَمَن.\nوتَرَكْتُ المالَ وغيرَه غامِداً: أي جامّاً وافراً.\nورَكيٌّ غامِدٌ: وارى التُّرَابُ ماءه فهو دِفَانٌ (¬٧٦).\nوالتَّغَمُّدُ: المَلْءُ.\nدمغ:",
    "pg": "5:46"
  },
  "غمر": {
    "def": "الغَمْرُ: الماءُ المُغَرِّقُ. وغِمَارُ البَحْرِ: جَماعَةُ الغَمْرِ (¬١٢٣). والسَّيِّدُ المِعْطاءُ. وفَرَسٌ غَمْرُ الجِرَاءِ: كثيرُ الجَرْيِ، والمَصْدَرُ الغَمْرُ. ورَجُلٌ غَمْرُ الخُلُقِ والرِّداءِ: أي كثيرُ المعروفِ سَخِيٌّ. والفَرَسُ الكثيرُ الجَرْيِ الجَوَادُ (¬١٢٤).\nواسْمُ مَوضِعٍ.\nوالغُمَرُ: قُدَيْحٌ صَغِيرٌ، والجميع الغِمْرَانُ.\nوالاغْتِمارُ (¬١٢٥): الاغْتِماسُ في غَمْرَةِ الحَرْبِ (¬١٢٦).\nوالغَمْرَةُ: مُنْهَمَكُ (¬١٢٧) الباطِل. وكذلك الحَرْبُ والشِّدَّةُ.\nوالمُغامِرُ: الذي يَرْمي بنفسِه في المَهالِكِ (¬١٢٨).\nوالغَمِيْرُ: نَباتٌ أخْضَرُ قد غَمَرَه اليَبِيْسُ. وهو من البَقْلِ: ما نَبَتَ (¬١٢٩) في أُصُولِ اليَبِيْسِ الحَوْليِّ فَغَمَرَه (¬١٣٠). ووَجَدْتُ أرضاً بها (¬١٣١) أغْمِرَاءُ لجَمْعِ الغَمِيرِ، وتَغَمَّرَ غَنَمُها.\nوغَمَرَ فلانٌ (¬١٣٢) فلاناً: إذا عَلاهُ (¬١٣٣) بفَضْلِه.\nوأغْمَرَني الحَرُّ: أي (¬١٣٤) فَتَرَ فاجْتَرَأْتَ (¬١٣٥) عليه. وغُمَارُ الناسِ (¬١٣٦): مُجْتَمَعُهم، وكذلك الغَمَارُ (¬١٣٧).\nوالغُمْرُ: الذي لم يُجَرِّبِ الأُمورَ، وهُمُ الأغْمارُ، ومَصْدَرُه الغَمَارَةُ والغُمُوْرَةُ. والغَمَرُ: الرَّجُلُ الغُمْرُ.\nودارٌ غامِرَةٌ: خَرَابٌ.\nوالغِمْرُ: الحِقْدُ.\nوالغَمَرُ: رِيْحُ اللَّحمِ والدَّنَسُ، غَمِرَتْ يَدُه غَمْراً (¬١٣٨).\nوالغُمْرَةُ: طِلاءٌ يُطْلى به العَرُوسُ.\nوالغَمِرَةُ والنَّمِرَةُ: ثَوْبٌ أسْوَدُ تَلْبَسُه الجَواري والعِبْدَانُ.\nوالتَّغْمِيْرُ بالشَّيْءِ: الرَّمْيُ به والدَّفْعُ.\nرغم:",
    "pg": "5:80-81"
  },
  "غمز": {
    "def": "الغَمْزُ: الإِشارةُ بالجَفْن والحاجِب (¬٤٩). والعَصْرُ باليَد.\nوالغَمّازَةُ: الجارِيَةُ الحَسَنَةُ الغَمْزِ للأعضاء.\nوالغَمِيزَةُ: ضَعْفَةٌ في العَمَل وجَهْلَةٌ في العَقْل.\nوالمَغامِزُ: المَعايِبُ. وما في الأمْرِ مَغْمَزٌ: أي مَطْمَعٌ، ومَعَابٌ أيضاً.\nوأغْمَزْتُ فيه إغمازاً: إذا اسْتَضْعَفْتَه. وقَوْمٌ أغْمازٌ: ضُعَفاءُ، واحِدُهم غَمزٌ.\nوهُم الذين لا خَيْرَ فيهم.\nوغَمَزْتُ بفلانٍ: سَعَيْت به في السِّرِّ.\nوالغَمْزُ في الدابَّة: من قِبَلِ الرِّجْل، والفِعْلُ يَغْمِزُ.\nوأغْمَزَتِ الناقَةُ: صارَ في سَنامِها شَحْمٌ حِينَ يُغْمَزُ أي يُلْمَسُ، وهو الغَمُوْزُ. الخارزنجيُّ (¬٤٥): خُذْهُ بِزَبَغِه (¬٤٦): أي بجُمْلتِه وحِدْثانِه.\nبغز\n(¬٤٧):\nالباغِزِيَّةُ: ضَرْبٌ من الثِّياب كالحَرِير.\nوالباغِزُ: النَّشاط، إنَّها لَذَاتُ باغِزٍ.\nوبَغَزْتُه بالسِّكِّين: [أي] (¬٤٨) بَزَغْته.\n\n\nغمز:\nالغَمْزُ: الإِشارةُ بالجَفْن والحاجِب (¬٤٩). والعَصْرُ باليَد.\nوالغَمّازَةُ: الجارِيَةُ الحَسَنَةُ الغَمْزِ للأعضاء.\nوالغَمِيزَةُ: ضَعْفَةٌ في العَمَل وجَهْلَةٌ في العَقْل.\nوالمَغامِزُ: المَعايِبُ. وما في الأمْرِ مَغْمَزٌ: أي مَطْمَعٌ، ومَعَابٌ أيضاً.\nوأغْمَزْتُ فيه إغمازاً: إذا اسْتَضْعَفْتَه. وقَوْمٌ أغْمازٌ: ضُعَفاءُ، واحِدُهم غَمزٌ.\nوهُم الذين لا خَيْرَ فيهم.\nوغَمَزْتُ بفلانٍ: سَعَيْت به في السِّرِّ.\nوالغَمْزُ في الدابَّة: من قِبَلِ الرِّجْل، والفِعْلُ يَغْمِزُ.\nوأغْمَزَتِ الناقَةُ: صارَ في سَنامِها شَحْمٌ حِينَ يُغْمَزُ أي يُلْمَسُ، وهو الغَمُوْزُ.\nزغم:",
    "pg": "5:29"
  },
  "غمس": {
    "def": "الغَمْسُ: إرْسالُ (¬٤٩) الشَّيْءِ في الماءِ وغيرِه.\nوالغَمّاسَةُ: من طَيْرِ الماءِ؛ غَطّاطٌ؛ يَغْتَمِسُ كثيراً.\nوالمُغامَسَةُ: أنْ يَرْمِيَ الرَّجُلُ بنَفْسِه في سِطَةِ الحَرْب. وهي-أيضاً-:\nالطَّعنةُ النافِذَةُ (¬٥٠).\nوالغَمِيْسُ: الغَمِيرُ تحتَ اليَبِيس.\nواليَمِينُ الغَمُوسُ: التي لا اسْتِثْناءَ فيها، وقيل: التي يُقْتَطَعُ فيها (¬٥١) الحَقُّ. والغَمُوْسُ: الشاةُ التي سُفِدَتْ مُنْذُ شَهْرٍ (¬٥٢) وأكْثَر (¬٥٣) ولم يَتَبَيَّنْ (¬٥٤) إيلادُها. وقيل: هي مِثْلُ الغَذَوِيَّةِ يُتَبَايَعُ (¬٥٥) بها وهي في بَطْن الأُمِّ.\nواخْتَضَبَتِ المَرْأةُ غَمْساً.\nوالغَمِيْسُ: الغالُّ من الأوْدِية، وجَمْعُه الغُمْسَان. وقيل: هو مجرى الماءِ.\nوالأجَمَةُ من القَصَب: غَمِيْسَةٌ.\nوغَمَسَ النَّجْمُ: غابَ.\nوالتَّغْمِيْسُ في الشُّرْب: التَّقْلِيلُ.\nمغس:",
    "pg": "5:19-20"
  },
  "غمص": {
    "def": "الغَمَصُ: في العَيْن، والقِطعة منه غَمَصَةٌ.\nوغَمَصَ الناسَ وغَمَطَ بهم: أي تَهَاوَنَ بهم وبحقُوقِهم.\nوالشِّعْرى الغُمَيْصَاءُ: هي الذِّراع السُّفلى.\nوغَمِصَ هذا الأمْرُ عَلَيَّ: أي تَغَيَّرَ وكَدِرَ.\nوإنَّه لَمَغْمُوْصٌ عليه: أي مَطْعُونٌ في دِينه وفِقْهِه.\nوغَمَصْتُ عليهِ قَوْلَه: عِبْتَه.\nولا تَغْمَصْ عَلَيَّ: أي لا تَغْضَبْ.\nويُقال للكَذّاب: هو غَمُوْصُ الحَنْجَرَةِ.\nويَمِيْنٌ غَمُوْصٌ: بمعنى غَمُوس.\nواغْتَمَصْتُ فلاناً: احْتَقَرْته. ومصْبَغَةُ الحُمْرَةِ (¬٣٣): هي الشَّدِيدَةُ الحُمْرَةِ.\nوأخَذْتُ الشَّيْءَ بِصِبْغِ ثَمَنِه: أي بِغَلاءٍ.\nصغب:\nمُهْمَلٌ عنده (¬٣٤).\nالخارزنْجِيُّ: يُقال لبَيْضَةِ البُرْغُوثِ والقَمْلةِ: صُغَابٌ، وجَمْعُه صِغْبانٌ.\nوالمَصْغَبَةُ (¬٣٥): لُغَةٌ في المَسْغَبَةِ، صِبْيَةٌ صِغَابٌ.\n\n\nغمص:\nالغَمَصُ: في العَيْن، والقِطعة منه غَمَصَةٌ.\nوغَمَصَ الناسَ وغَمَطَ بهم: أي تَهَاوَنَ بهم وبحقُوقِهم.\nوالشِّعْرى الغُمَيْصَاءُ: هي الذِّراع السُّفلى.\nوغَمِصَ هذا الأمْرُ عَلَيَّ: أي تَغَيَّرَ وكَدِرَ.\nوإنَّه لَمَغْمُوْصٌ عليه: أي مَطْعُونٌ في دِينه وفِقْهِه.\nوغَمَصْتُ عليهِ قَوْلَه: عِبْتَه.\nولا تَغْمَصْ عَلَيَّ: أي لا تَغْضَبْ.\nويُقال للكَذّاب: هو غَمُوْصُ الحَنْجَرَةِ.\nويَمِيْنٌ غَمُوْصٌ: بمعنى غَمُوس.\nواغْتَمَصْتُ فلاناً: احْتَقَرْته.\nمغص:",
    "pg": "5:10"
  },
  "غمط": {
    "def": "غَمَطَ النِّعمةَ والعافيةَ: إذا لم يَشْكُرْها.\nوالغَمْطُ: كالغَمْج، والفِعْلُ يُغامِطُ [/١٤٥ ب].\nوالإِغْمَاطُ: المُلازَمَةُ والمُدَاوَمَةُ، أغْمَطَتْ عليه الحُمّى: دامَتْ، وحُمّى مُغْمِطَةٌ (¬٣٤).\nواغْتَمَطْتُ الرَّجُلَ: إذا حاضَرْتَه فَسَبَقْتَه بعد ما سَبَقَك، وكذلك في الكلام إذا قَهَرْتَه. وسَمَاءٌ غَمَطى: أغْمَطَتْ بالسَّحاب يَوْمَيْنِ أو ثلاثةً.\nطمغ\n(¬٣٥):",
    "pg": "5:34-35"
  },
  "غمل": {
    "def": "غَمَلْتُ الأدِيْمَ: إذا جَعَلْتَه في غُمَّةٍ لِيَتَفَسَّخَ (¬٥٠) صُوفُه عنه.\nوالغُمْلُولُ (¬٥١): حَشِيْشَةٌ تُؤْكَلُ مطبوخَةً. والغَمَالِيْلُ: الرَّوابي. وكُلُّ ما اجْتَمَعَ نَحْوُ الشَّجَرِ والغَمَامِ. وقَضِيْبُ الحِمارِ.\nوالتَّغَمُّلُ: التَّوَسُّعُ في المال.\nوالغَمْلُ: الإِصلاح.\nوغَمِلَ النَّبْتُ: رَكِبَ بعضُه بَعْضاً حتى يَسْوَدَّ ويَعْفَنَ.\nولَحْمٌ مَغْمُولٌ ومَغْمُونٌ: مُغَطّى.\nوالغُمْلُولُ: الخَمَرُ من الأرضِ.\nمغل:",
    "pg": "5:89-90"
  },
  "غمن": {
    "def": "غَمَنْتُ الجِلْدَ لِيَلِيْنَ ويَحْتَمِلَ الدِّباغَ (¬٢٤).\nوانْغَمَنَ في الأرض، وغُمِنَ فيها: إذا أُدْخِلَ فيها.\nولَحْمٌ مَغْمُونٌ ومَغْمُولٌ: واحِدٌ (¬٢٥). (¬١)\n\nفغم:",
    "pg": "5:94-95"
  },
  "غمى": {
    "def": "الغِمَاءُ: سَقْفُ البَيْتِ، غَمَّيْتُ البَيْتَ والإِناءَ: غَطَّيْتَه. وغَمى بَيْتَه يَغْمُوه ويَغْمِيه.\nوفي السَّماءِ غَمْيٌ: أي غَيْمٌ. وأغْمى (¬١) يَوْمُنا: دامَ غَيْمُه، وكذلك لَيْلَةٌ مُغْمَاةٌ.\nوأُغْمِيَ على فلانٍ: إذا (¬٢) ظُنَّ أنَّه [قد] (¬٣) ماتَ، وغُمِيَ عليه:\nمِثْلُه (¬٤)، فهو مَغْمِيٌّ عليه.\nوالغَمى: [الرَّجُلُ] (¬٥) المَرِيضُ؛ والطَّلى كذلك، والاثنانِ غَمَيَانِ (¬٦)، والجميع أغْماء.\nوتقول غَمَا واللَّهِ لَأفْعَلَنَّ: بمعنى أمَا واللَّهِ. غيم:",
    "pg": "5:145-146"
  },
  "غنت": {
    "def": "مُهْمَلٌ عنده (¬١٠).\n[الخارزنجي] (¬١١): أغْنَتَه إغْناتاً حتى غَنِتَ غَنَتاً: أي أهْلَكَه.\nوغَنَتَ نَفْساً في الشُّرْب.\nوأغْنِتْ دابَّتَكَ: أشْرِعْها. واغْتَلَتَني فلانٌ وتَغَلَّتَني: [أي] (¬٨) أخَذَني (¬٩) على غِرَّةٍ.\nوالغَلُوْتُ: الذي يَغْلَتُ كثيراً.\n\n\nنتغ:\nأنْتَغَ الرَّجُلُ إنْتَاغاً: إذا ضَحِكَ ضِحْكَ المُسْتَهْزئِ خَفِيّاً.\nنغت:\nالنَّغْتُ: جَذْبُ الشَّعْرِ.\nغنت:\nمُهْمَلٌ عنده (¬١٠).\n[الخارزنجي] (¬١١): أغْنَتَه إغْناتاً حتى غَنِتَ غَنَتاً: أي أهْلَكَه.\nوغَنَتَ نَفْساً في الشُّرْب.\nوأغْنِتْ دابَّتَكَ: أشْرِعْها.\n\n\nبغت:",
    "pg": "5:48"
  },
  "غنث": {
    "def": "غَنِثَ من اللَّبَنِ يَغْنَثُ غَنَثاً: وهو أنْ يَشْرَبَ ثُمَّ يَتَنَفَّسَ. وما لَكَ مُتَغَنِّثاً: أي خَبيثَ (¬٣٦) النَّفْسِ.\n\n\nمُهْمَلٌ (¬٣٧).\n[فثغ] والغَلْثى: شَجَرَةٌ من شَجَرِ الجِبالِ يُغَلَّثُ بها للسِّباع والطَّيْرِ (¬٣٤).\nوالغَلِثُ والغَلَثِيُّ: الدّاهِيَةُ.\nوشَعرٌ غَلِيثٌ: أشْمَطُ.\nوالغَلَثُ في الغَضَب: الاخْتِلاطُ.\nوسِقَاءٌ مَغْلُوثٌ: مَدْبُوغٌ بالتَّمر أو البُسْرِ (¬٣٥).\n\n\nغنث:\nغَنِثَ من اللَّبَنِ يَغْنَثُ غَنَثاً: وهو أنْ يَشْرَبَ ثُمَّ يَتَنَفَّسَ. وما لَكَ مُتَغَنِّثاً: أي خَبيثَ (¬٣٦) النَّفْسِ.\n\n\nمُهْمَلٌ (¬٣٧).\n[فثغ]\n(¬٣٨):",
    "pg": "5:59"
  },
  "غنص": {
    "def": "مُهْمَلٌ عنده (¬٢١).\nالغَنَصُ (¬٢٢): ضِيْقُ الصَّدْرِ. نغص (¬١٨):\nنَغِصَ (¬١٩) الرَّجُلُ نَغَصاً: إذا لم تَتِمَّ له هَنَاءتُه (¬٢٠)، ويُشَدَّد أيضاً.\nوالنَّغَصُ: في المَشْرَب أيضاً.\nغنص:\nمُهْمَلٌ عنده (¬٢١).\nالغَنَصُ (¬٢٢): ضِيْقُ الصَّدْرِ.\n\n\nغفص:",
    "pg": "5:8"
  },
  "غنظ": {
    "def": "الغَنْظُ: الهَمُّ اللازِمُ، إنَّه لَمَغْنُوظٌ، وغَنَظَه هذا الأمْرُ يَغْنِظُه ويَغْنُظُه.\nوالغَنَظُ: تَغَيُّرُ النَّبْتِ من الحَرِّ.\nورَجُلٌ غِنْظِيَانٌ، وإنَّه لَيُغَنْظي بالناسِ: أي يَسْخَرُ منهم (¬١).  (¬١)\n(¬٢)\nغذر (¬٣):\nمُهْمَلٌ عنده (¬٤).\nالخارزنجيُّ: الغَيْذَرَةُ (¬٥): الشَّرُّ.\nوغَيْذَرَ الرَّجُلُ: أكْثَرَ الكلامَ وَخَلَّطَ، وإنَّه لَكَثِيرُ الغَيَاذِرِ.\nوالغَيْذَارُ: الحِمَارُ، وجَمْعُه غَيَاذِيْرُ.\n\n\n[مُهْمَلاتٌ أيضاً] (¬٧). ذلغ (¬٨):\nالخارزنجيُّ: الذَّلَغُ في شَفَةِ الانسان: كالهَدَل في مِشْفَرِ البَعِير، ذَلِغَتْ شَفَتُه: أي انْقَلَبَتْ، فهو أذْلَغُ، والأُنثى ذَلْغاءُ (¬٩).\nوالأذْلَغِيُّ: الذَّكَرُ الذي يُمْذي، والمِذْلَغُ مِثْلُه.\nوالذّالِغُ: لَقَبُ الانسانِ في سُوْءِ ضحكِه.\nوالذَّلغُ (¬١٠): الأكْلُ لِمَا لانَ.\nوالانْذِلاغُ: إرْطابُ النَّخلِ.\nوذَلَغَ الرَّجُلُ الطَّعامَ: إذا (¬١١) أكَلَه أكْلاً قَبيحاً.\nوأرْضٌ مُتَذَلِّغَةٌ (¬١٢).\nوأمْرٌ ذالِغٌ مُتَذَلِّغٌ (¬١٣): أي ليس دُوْنَه شَيْءٌ.\nوذَلَغْتُ الطَّعامَ: سَغْسَغْته (¬١٤).\nغلذ (¬١٥):\nمُهْمَلٌ عنده (¬١٦).\nشَيْءٌ غَلِيْذٌ: بمعنى غَلِيظ.\n\n\nمُهْمَلاتٌ عنده (¬١٧). [غنذ] (¬١٨):\nالخارزنجيُّ: إنَّ فُلانةَ لَتُغَنْذي (¬١٩) بالناس: أي تُغْري بِهم وتَسْخَرُ منهم، وقد غَنَذَتْ.\n\n\nغذم:",
    "pg": "5:51-54"
  },
  "غنف": {
    "def": "الغَيْنَفُ (¬٢): غَيْلَمُ الماءِ في مَنْبَعِ الآبارِ، بَحْرٌ ذو غَيْنَفٍ (¬٣). (¬١)\n\nغنف:\nالغَيْنَفُ (¬٢): غَيْلَمُ الماءِ في مَنْبَعِ الآبارِ، بَحْرٌ ذو غَيْنَفٍ (¬٣).\nنغف:",
    "pg": "5:91"
  },
  "غنم": {
    "def": "الغَنَمُ: الشّاءُ، هذه غَنَمٌ (¬١٨) للجَماعَة. وَتَغَنَّمْتُ غَنَماً: اتَّخَذْتها. ولفلانٍ غَنَمانِ: أي قَطِيعانِ.\nوالغُنْمُ: الفَوْزُ بالشَّيْءِ من غَيْر (¬١٩) مَشَقَّةٍ. والاغْتِنامُ: انْتِهازُه.\nوالغَنِيْمَةُ: الفَيْءُ. وغَنَّمْتُه فاغْتَنَمَ. والغِنَامَةُ: الغَنِيْمَةُ، وجَمْعُها غِنَامٌ. وغُنَاماكَ أنْ تَلْحَقَه: أي جُهْدَك.\nوبَنُو غَنْمٍ: حَيٌّ من العَرَب (¬٢٠).\nنغم:",
    "pg": "5:93-94"
  },
  "غنى": {
    "def": "الغِنى في المال-مَقْصُورٌ-. وتَغَنّى: في معنى اسْتَغْنى. والغُنْيَةُ: اسْمٌ من الاسْتِغْناءِ عن الشَّيْءِ.\nو ١٦ - في الحديث (¬٨): «ليس مِنّا مَنْ لم يَتَغَنَّ (¬٩) بالقُرآن». أي لم يَسْتَغْنِ. ويُقال: تَغانَيْتُ وتَغَنَّيْتُ. والغُنْيانُ: الغِنى.\nوالغِنَاءُ في الصَّوْتِ-مَمْدُودٌ-، غَنّى يُغَنّي أُغْنِيَةً (¬١٠) وغِنَاءً.\nوالغَنَاءُ: الإِجْزَاءُ (¬١١)، رَجُلٌ مُغْنٍ، وغَنِيَ عنه فهو غانٍ. وأغْنَيْتُ عنكَ مُغْنَاةَ فلانٍ ومَغْناتَه (¬١٢).\nوغَنِيَ القَوْمُ في المَحَلَّة: طالَ مُقَامُهم فيها. ومَغْنى الدارِ: مَوضِعُ الحُلُولِ والمَقام، والجميع المَغاني.\nوالغانِيَةُ: الشابَّةُ المُتَزَوِّجَةُ، والجميع الغَوَاني.\nوالمُغاناةُ (¬١٣): تَكْلِيْمُكَ الصَّبِيَّ بما يَهْوى.\nويقولون: مَكانُ كذا غَنَا (¬١٤) من فلانٍ: أي مَئنَّةٌ (¬١٥).\nوما غَنِيْتُ فلاناً: أي لم ألْقَه.\nوهو مَغْنىً من فلانٍ: أي حَرىً منه.\nورَمْلُ الغِنَاءِ: مَوضِعٌ. نغى:",
    "pg": "5:135-136"
  },
  "غهب": {
    "def": "الغَهَبُ: الغَفْلَةُ عن الشَّيْءِ من غَيْرِ تَعَمُّدٍ، غَهِبْتُ أَغْهَبُ غَهَباً. والغَيْهَبُ: الظُّلْمَةُ. والغَيَاهِبُ: السُّوْدُ. ولَيْلٌ غَيْهَبٌ: مُظْلِمٌ.\nوالغَيْهَبَةُ: الجَلَبَةُ في القِتالِ.\nوالغَيْهَبَانُ: البَطْنُ.\nوفي أَحَاجِيِّهم: ما ثَلْثُ دُجَّه يَحْمِلْنَ دُجَّه الى الغَيْهَبَان فالمِنْتَجَه (¬٧).\n[و] (¬٨) الغِهِبّى: أوَّلُ الشَّبَابِ، من غَهِبْتُ عن الشَّيْءِ: أي سَهَوْتَ عنه.\n\n\nأُهْمِلَتْ عنده.\nهمغ (¬٩):\nالخارزنجيُّ: الهِمْيَغُ (¬١٠): المَوْتُ الوَحِيُّ، من قَوْلهم: هَمَغَ رَأْسَه: أي شَدَخَه.\nوقَرْحَةٌ مُنْهَمِغَةٌ: مُبْتَلَّةٌ.\nوانْهَمَغَ الشَّيْءُ: انْفَسَخَ (¬١١).\nوالهَيْمَغُ: شَجَرَةٌ ثَمَرُها المَغْدُ.\nغهم (¬١٢):\nيُقال للظُّلْمَةِ: غَيْهَمٌ. شهق:",
    "pg": "3:335-337"
  },
  "غوج": {
    "def": "جَمَلٌ غَوْجُ اللَّبَانِ: أي عَرِيْضُ الصَّدْرِ، وكذلك الفَرَسُ.\nوغاجَ في المَشْي: [أي] (¬١) تَثَنّى، [يَغُوجُ] (¬٢). (و. ا. ي)\nغشو:",
    "pg": "5:100-101"
  },
  "غور": {
    "def": "غارَ الرَّجُلُ: أتى الغَوْرَ وهو تِهَامَةُ، و [يُقال] (¬١٢) أغارَ. والمُسْتَغارُ (¬١٣):\nالذي يُريدُ هُبُوطَ أرْضٍ وغَوْرٍ (¬١٤).\nوغَوْرُ كُلِّ شَيْءٍ: بُعْدُ قَعْرِه (¬١٥). [و] (¬١٦) غارَتِ النُّجُومُ. وغارَ القَمَرُ والعَيْنُ والماءُ تَغُوْرُ غُؤُوْراً. وغارَتِ الشَّمْسُ غِيَاراً. وغَوَّرَ النَّجْمُ أيضاً.\nوغَوَّرَ الرَّجُلُ (¬١٧) تَغْوِيراً: إذا قالَ قَيْلُولةً. والغائرةُ: القائلةُ (¬١٨). وغارَ النَّهارُ: اشْتَدَّ حَرُّه. والغائرةُ: الهاجِرَةُ. والتَّغْوِيْرُ: النُّزُوْلُ عند الغائرة. والغَوْرَةُ:\nالغائرةُ.\nوغارا الفَمِ (¬١٩): نِطْعَاهُ في الحَنَكَيْنِ. ومَغَارَةٌ في الجَبَل كالسَّرَب. ولُغَةٌ في الغَيْرَة. ونَبْتٌ طَيِّبُ الرِّيحِ على الوُقُود. والجَمْعُ الكثيرُ من الناس. والقَبِيلةُ العَظِيمةُ.\nوالغارانِ: البَطْنُ والفَرْجُ، هو عَبْدُ غارَيْهِ (¬٢٠).\nوالغارُ: الفَسَادُ.\nومَثَلٌ (¬٢١) «عَسى الغُوَيْرُ أبْؤسا (¬٢٢)» وهو ماءٌ، وقيل: غارٌ.\nوالغارَةُ، والفِعْلُ الإِغارَةُ. ورَجُلٌ مِغْوارٌ: كثير الغارات. والمُغِيرةُ: خَيْلٌ قد أغارَتْ. والغِيَرُ: جَمْعُ الغارة.\nوالغارَةُ: العَدْوُ، يُقال: عَدَا غَارَةَ (¬٢٣) الثَّعْلَبِ. وأغارَ الرَّجُلُ: أسْرَعَ في عَدْوِه. وفي المَثَل (¬٢٤): «أشْرِقْ ثَبِيْرُ كَيْما نُغِيرَ (¬٢٥)».\nواسْتَغَارَ الجُرْحُ: إذا تَوَرَّمَ. وغارَ فيه الطَّعامُ والشَّرابُ يَغُوْرُ: أي نَجَعَ.\nوما اغْتَرْتُ بشَيْءٍ: أي ما انْتَفَعْت.\nوهذا كلامٌ لا غُوْرَ له-بضمِّ الغَيْن-: أي هو باطِلٌ لا نَفْعَ فيه.\nواسْتَغْوِرِ اللَّهَ: أي اسْتَمِرْهُ.\nوغارَني يَغُوْرُني (¬٢٦): من الدِّيَة.\nوالغائرَةُ: السُّرَّةُ (¬٢٧).\nغير:",
    "pg": "5:123-125"
  },
  "غوص": {
    "def": "الغَوْصُ: الدُّخُولُ تحت الماء. ومَوضِعٌ يُخْرَجُ منه اللُّؤْلُؤ، والغاصَةُ:\nمُسْتَخْرِجُوه.\nوالهاجِمُ على الشَّيْءِ (¬١): غائصٌ وغَوّاصٌ.\nوالمَغَاصُ: أعْلى السّاقِ. (و. ا. ي)\nغوص:\nالغَوْصُ: الدُّخُولُ تحت الماء. ومَوضِعٌ يُخْرَجُ منه اللُّؤْلُؤ، والغاصَةُ:\nمُسْتَخْرِجُوه.\nوالهاجِمُ على الشَّيْءِ (¬١): غائصٌ وغَوّاصٌ.\nوالمَغَاصُ: أعْلى السّاقِ.\nصوغ:",
    "pg": "5:105"
  },
  "غوط": {
    "def": "غُوْطَةُ: مَوضعٌ بالشّام.\nوالغائطُ والغَوْطُ: المُطْمَئنُّ من الأرض، والجميع الغِيْطانُ والأغْوَاطُ.\nوالتَّغَوُّطُ: فِعْلُ الغائطِ.\nوغاطَ في الأرض يَغُوْطُ ويَغِيْطُ (¬٢): بمعنى غارَ (¬٣).\nوغاطَتِ الأنْسَاعُ (¬٤) في جَنْبِ البَعِيرِ: دَخَلَتْ فيه.\nوالغَوْطُ: عُمقُ الأرضِ الأبْعَدُ الذي يُفْضي (¬٥) إلى مُعْظَم الماء.\nوالغَوْطُ: الثَّرِيْدُ، [و] (¬٦) غَوَّطَ الرَّجُلُ: لَقِمَ.\nووَقَعَ في غَوْطَةٍ: أي (¬٧) في أمْرٍ شدِيدٍ.\nوالغاطُ: مِثْلُ الغَوْط.\nوغاطَ يَغِيْطُ: أي غابَ في الأرْضِ. غطى:",
    "pg": "5:111-112"
  },
  "غول": {
    "def": "الغَوْلُ: بُعْدُ المَفازَةِ (¬٨)؛ وذلك أنَّها تَغْتالُ (¬٩) سَيْرَ القَوْمِ.\nوغالَهُ المَوْتُ: أهْلَكَه.\nوالغُوْلُ: المَنِيَّةُ. والسَّعالي، تقول (¬١٠): تَغَوَّلَتْهم الغِيْلانُ والغِوَلَةُ (¬١١).\nوالغَوْلُ: الصُّدَاعُ.\nوالغَوْلانُ: نَباتٌ.\nوالمِغْوَلُ: شِبْهُ مِشْمَلٍ إِلاَّ أنَّه أصْغَرُ وأدَقُّ.\nوالمُغاوَلَةُ: المُبَادَرةُ إلى الشَّيْءِ.\nوهُوَ في عَيْشٍ أغْوَلَ: أي ناعِمٍ، وغُوَّلٍ (¬١٢) كذلك.\nوفَرَسٌ ذاتُ مِغْوَلٍ: أي ذاتُ سَبْقٍ.\nوالغَوْلانُ: الحَمْضُ نَفْسُه. وفَعَلَ ذلك (¬٦) في غَلْوَةِ شَبابِه: أي في عُنْفُوانِه، وغُلَوائه (¬٧).\nوالغَلاءُ -مَمْدُودٌ-: سَمَكَةٌ نَحْوٌ من شِبْرٍ، وجَمْعُه أغْلِيَةٌ.\n[غلي]\nوغَلَتِ القِدْرُ تَغْلي غَلَياناً وغَلْياً.\nوالغالِيَةُ: مَعْروفةٌ.\nغول:\nالغَوْلُ: بُعْدُ المَفازَةِ (¬٨)؛ وذلك أنَّها تَغْتالُ (¬٩) سَيْرَ القَوْمِ.\nوغالَهُ المَوْتُ: أهْلَكَه.\nوالغُوْلُ: المَنِيَّةُ. والسَّعالي، تقول (¬١٠): تَغَوَّلَتْهم الغِيْلانُ والغِوَلَةُ (¬١١).\nوالغَوْلُ: الصُّدَاعُ.\nوالغَوْلانُ: نَباتٌ.\nوالمِغْوَلُ: شِبْهُ مِشْمَلٍ إِلاَّ أنَّه أصْغَرُ وأدَقُّ.\nوالمُغاوَلَةُ: المُبَادَرةُ إلى الشَّيْءِ.\nوهُوَ في عَيْشٍ أغْوَلَ: أي ناعِمٍ، وغُوَّلٍ (¬١٢) كذلك.\nوفَرَسٌ ذاتُ مِغْوَلٍ: أي ذاتُ سَبْقٍ.\nوالغَوْلانُ: الحَمْضُ نَفْسُه.\nغيل:",
    "pg": "5:130"
  },
  "غيب": {
    "def": "غابَ الرَّجُلُ يَغِيْبُ غَيْبَةً.\nوغابَتِ الشَّمْسُ [تَغِيْبُ] (¬٣٠) غِيَاباً.\nوالمُغِيْبَةُ: المَرْأةُ التي غابَ عنها زَوْجُها، ومنه\n١٦ - الحَدِيث: «لا يَخْلُوَنَّ رَجُلٌ بِمُغِيْبَةٍ». ويُقال مُغِيْبٌ أيضاً.\nوالغِيْبَةُ: مَعْرُوفةٌ (¬٣١).\nوالمُغْيِبُ: الظَّبْيَةُ التي أغابَتْ وَلَدَها في غَيْبٍ من الأرض؛ على مِثالِ مُغْزِلٍ.\nوغَيَّبَانُ العُوْدِ: عُرُوْقُه وما تَغَيَّبَ منه.\nوشَرِبَتِ الدابَّةُ حتّى وارَتْ غُيُوْبَ كُلاها: وهي الخَمْصَةُ التي تكون في مَوضِع الكُلْيَةِ، الواحِدُ (¬٣٢) غَيْبٌ. (و. ا. ي)\nغمى:",
    "pg": "5:144-145"
  },
  "غيد": {
    "def": "الغادَةُ: الفَتاةُ الناعِمَةُ، وكذلك الغَيْدَاءُ والأغْيَدُ.\nوبَرْدِيَّةٌ غَيْدانَةٌ: غَضَّةٌ، وكذلك كلُّ شَجَرٍ غَضٍّ. والأغْيَدُ: الوَسنانُ المائلُ العُنُقِ. وهو يَتَغايَدُ في مَشْيِه.\nوإنّه لَفي غَيْدانِ شَبابِه: أي حِدْثانِه.\nغدو:",
    "pg": "5:113-114"
  },
  "غيذ": {
    "def": "مُهْمَلٌ (¬٤).\nالخارزنجيُّ (¬٥): المُغْتاذُ لُغَةٌ في المُغْتاظ (¬٦). (و. ا. ي)\nغثى:",
    "pg": "5:118-119"
  },
  "غير": {
    "def": "الغَيْرَانُ: الرَّجُلُ الغَيُوْرُ، والجمع: الغَيَارى والغُيُرُ والغِيَرُ (¬٢٨). والمَرْأةُ (¬٢٩) غَيْرى غَيُوْرٌ. ورَجُلٌ غارٌ غَيُوْرٌ. وهو لا يَتَغَيَّرُ على أهْلِه: أي لا يَغَارُ.\nويقولون (¬٣٠): «أغْيَرُ من الفَحْل».\nوالإِغارَةُ: الدَّفْعَةُ على القَوْم. وشِدَّةُ فَتْلِ الخَبْلِ (¬٣١).\nوفَرَسٌ مُغَارٌ: شَدِيدُ المَفاصِلِ.\nوالغَيْرُ: النَّفْعُ.\nوالغِيْرَةُ [/١٥١ ب]: المِيْرَةُ، غَارَهم يَغِيْرُهم ويَغُوْرُهم: مارَهُم، وهو الغِيَارُ وجَمْعُها غِيَرٌ. والدِّيَةُ-أيضاً-، وغَيَّرَ فلانٌ فلاناً: أعطاه الدِّيَةَ (¬٣٢). وغارَ الغَيْثُ الأرضَ يَغِيْرُها: إذا سَقَاها (¬٣٣). وغارَنَا اللَّهُ بخَيْرٍ. وأرْضٌ مَغِيْرَةٌ ومَغْيُورَةٌ.\nوغِرْنا بخَيْرٍ: أي غِثْنا.\nوغارَ فيه الطَّعامُ يَغِيْرُ: [أي] (¬٣٤) نَجَعَ.\nوغَيْرُ: يكونُ استثناءً ويكون (¬٣٥) اسْماً، وبعضُ العَرَبِ يُثَنِّيه ويَجْمَعُه.\nوالغَيْرُ: التَّغْيِيْرُ، وكذلك الغِيَرُ في قَوْله:\nقد بَلَغَ الماءُ الرُّبى فلا غِيَرْ …\nويُقال للكَذِباتِ: بَنَاتُ غَيْرٍ.\nوغايَرْتُه بسِلْعَتي: أي بادَلْتُه.\nوأغارَ فلانٌ إلى بني فلانٍ إغارَةً: إذا أتاهم ليَنْصُرَهم أو ليَنْصُرُوه.\nوغر:",
    "pg": "5:125-126"
  },
  "غيض": {
    "def": "غاضَ الماءُ يَغِيْضُ غَيْضاً ومَغَاضاً. والمَغِيْضُ: المَوضِعُ. وغِيْضَ ماءُ البَحرِ. وغِضْتُه: فَجَّرْته إلى مَغِيْضٍ. وانْغاضَ الماءُ.\nوالغَيْضَةُ: معروفةٌ، والجميع الغِيَاضُ.\nوالغِيْضُ (¬١): الطَّلْعُ. (و. ا. ي)\nغيض:\nغاضَ الماءُ يَغِيْضُ غَيْضاً ومَغَاضاً. والمَغِيْضُ: المَوضِعُ. وغِيْضَ ماءُ البَحرِ. وغِضْتُه: فَجَّرْته إلى مَغِيْضٍ. وانْغاضَ الماءُ.\nوالغَيْضَةُ: معروفةٌ، والجميع الغِيَاضُ.\nوالغِيْضُ (¬١): الطَّلْعُ.\nغضى:",
    "pg": "5:103"
  },
  "غيظ": {
    "def": "غِظْتُه، وأنا أغِيْظُه غَيْظاً.\nوالتَّغَيُّظُ: الاغْتِيَاظ.\nوبَنُو غَيْظٍ: حَيٌّ من قَيْسٍ.\nوفلانٌ يُغايِظُ فلاناً: إذا باراه فَصَنَعَ مِثْلَ صَنِيْعِه. (و. ا. ي) [/١٥١ أ]\nغذو:",
    "pg": "5:117-118"
  },
  "غيف": {
    "def": "التَّغَيُّفُ: التَّمَيُّلُ في العَدْوِ والمَشْي.\nوغَيَّفَ الرَّجُلُ: فَرَّ، وكذلك في القِتال.\nوالغَيَّفَانُ: المَرِحُ.\nوأغَفْتُ الشَّجَرَةَ (¬٣) فَغافَتْ، وهي (¬٤) تَغِيْفُ بأغصانها يَمِيناً وشِمالاً، وشَجَرَةٌ غَيْفاءُ.\nوالأغْيَفُ: كالأغْيَدِ من غير نُعَاسٍ. وهو في عَيْشٍ أغْيَفَ: أي ناعِمٍ.\nوالغافُ: يَنْبُوتٌ (¬٥) عِظامٌ كالشَّجَر.\nوالغَيْفُ: جَماعَةٌ من الطَّير.\nوالغَيّافُ: الذي طالتْ لِحْيَتُه وعرضَتْ من كلِّ جانبٍ، وقَوْمٌ غَيّافُوْنَ.\nغفو:",
    "pg": "5:137-138"
  },
  "غيل": {
    "def": "الغِيْلَةُ: الاغْتِيال. والغائلةُ: فِعْلُ المُغْتالِ. والغِيْلُ: مَكانٌ من الغَيْضَة فيه ماءٌ مَعِينٌ. وتَغَيَّلَ الرَّجُلُ: دَخَلَه.\nوالغَيّالُ: الأسَدُ.\nوالغَيْلُ: إرضاعُ الصَّبيِّ على الحَمْل (¬١٣)، والفِعْلُ أغْيَلَتْ وأغالتْ، وصَبيٌّ مُغَالٌ ومُغْيَلٌ (¬١٤).\nوالغَيْلَةُ: المَرْأةُ السَّمِيْنَةُ.\nوالغَيْلُ: الساعِدُ الرَّيّانُ. والأغْيَلُ: المُمْتَلِئُ العَظِيمُ. واغْتَالَ الصَّبيُّ اغْتِيالاً. ومِعْصَمٌ مُغْتالٌ.\nوالأغْيَالُ: الخُطُوطُ، واحِدُها غَيْلٌ.\nوأَغْيَلتِ (¬١٥) الغَنَمُ والبَقَرُ: نُتِجَتْ في السَّنَة مَرَّتَيْنِ، ومنه اشْتُقَّ اسْمُ غَيْلانَ.\nوتَغَيَّلَ القَوْمُ: كَثُروا (¬١٦) وكَثُرَتْ أمْوالُهم (¬١٧).\nوغالَ فلاناً غَيْلٌ (¬١٨): أي بَلَدٌ.\nوالغَيْلُ: الماءُ الذي يَجْري (¬١٩) على وَجْهِ الأرضِ،\nو ١٦ - في الحديث (¬٢٠): «ما سُقِيَ بالغَيْلِ ففيه العُشْرُ».\nوأرْضٌ غَيْلَةٌ (¬٢١): وهي إلى البُعْدِ ما هيَ. وغل:",
    "pg": "5:130-132"
  },
  "غيم": {
    "def": "الغَيْمُ: مَعْروفٌ، غامَتِ السَّمَاءُ وتَغَيَّمَتْ وأغامَتْ.\nوالغَيْمُ: الغَيْظُ. والعَطَشُ، والغَيْمَانُ: العَطْشانُ.\nوالغُيَامُ: داءٌ يأْخُذُ الإِبلَ.\nوأغْيَمَ الرَّجُلُ: أقامَ.\nوالتَّغْيِيْمُ: أن يُرَفْرِفَ الطائرُ فَوْقَ رَأْسِكَ و (¬٧) لا يَبْرَحُ. غيم:\nالغَيْمُ: مَعْروفٌ، غامَتِ السَّمَاءُ وتَغَيَّمَتْ وأغامَتْ.\nوالغَيْمُ: الغَيْظُ. والعَطَشُ، والغَيْمَانُ: العَطْشانُ.\nوالغُيَامُ: داءٌ يأْخُذُ الإِبلَ.\nوأغْيَمَ الرَّجُلُ: أقامَ.\nوالتَّغْيِيْمُ: أن يُرَفْرِفَ الطائرُ فَوْقَ رَأْسِكَ و (¬٧) لا يَبْرَحُ.\nوغم:",
    "pg": "5:146"
  }
}